{
  "ComponentIndexes": {},
  "ControlUniqueGuids": {},
  "ControlUniqueIds": {
    "address_card": 137,
    "address_card_1": 270,
    "address_input": 139,
    "address_input_1": 272,
    "address_label": 138,
    "address_label_1": 271,
    "ALVARIA ID_Column1": 738,
    "Alvaria_ID": 580,
    "App": 1,
    "BILLABILITY_Column1_1": 731,
    "BILLABILITY_DataCard PRMp1_1": 470,
    "BILLABILITY_DataCardOCFP": 561,
    "BILLABILITY_LTMDataCard": 693,
    "BILLABILITY_LTMDataCard2": 632,
    "BILLABILITY_OTDataCard": 322,
    "BILLABILITY_OTDataCard1": 42,
    "BILLABILITY_PRMDataCard2_2": 409,
    "btnFirstPageNext": 500,
    "btnLTMultipleBack": 712,
    "btnLTMultipleBack_1": 649,
    "btnLTMultipleBack_2": 84,
    "btnLTMultipleBack_3": 145,
    "btnLTMultipleBack_4": 278,
    "btnLTMultipleReview": 713,
    "btnLTMultipleReview_1": 650,
    "btnLTMultipleReview_2": 85,
    "btnLTRemove": 648,
    "btnLTRemove_1": 277,
    "btnOCEPBack": 219,
    "btnOCEPUpdate": 220,
    "btnOCFPBack": 589,
    "btnOCFPReview": 590,
    "btnOCFPSave": 588,
    "btnOCSPBack": 745,
    "btnOCSPEdit": 718,
    "btnOCSPRemove": 719,
    "btnOCSPSubmit": 746,
    "btnOTBack": 366,
    "btnOTRemove": 83,
    "btnOTReview": 367,
    "btnOTSave": 365,
    "btnPRMultipleBackp1_1": 489,
    "btnPRMultipleBackp2_1": 426,
    "btnPRMultipleReviewp1_1": 490,
    "btnPRMultipleSubmitp2_1": 427,
    "btnPRRemovep2_3": 425,
    "BUSINESS UNIT_Column1_1": 726,
    "BUSINESS UNIT_DataCard PRMp1_1": 449,
    "BUSINESS UNIT_DataCardOCFP": 533,
    "BUSINESS UNIT_LTMDataCard": 672,
    "BUSINESS UNIT_LTMDataCard2": 610,
    "BUSINESS UNIT_OTDataCard": 304,
    "BUSINESS UNIT_OTDataCard1": 24,
    "BUSINESS UNIT_PRMDataCard_4": 387,
    "Button1": 587,
    "Button2": 144,
    "Button5": 488,
    "Button6": 711,
    "campaign_card": 116,
    "campaign_card_1": 249,
    "CAMPAIGN_Column1_1": 729,
    "campaign_label": 117,
    "campaign_label_1": 250,
    "campaign_value": 118,
    "campaign_value_1": 251,
    "cbLTMultipleBillability": 694,
    "cbLTMultipleBusUnit": 673,
    "cbLTMultipleClient": 685,
    "cbLTMultipleLOB": 688,
    "cbLTMultiplePosition": 679,
    "cbLTMultipleSubLOB": 691,
    "cbLTMultipleSubUnit": 676,
    "cbLTMultipleSupervisor": 697,
    "cbLTMultipleSupervisorEmail_1": 700,
    "cbLTMultipleSupervisorEmpID_1": 703,
    "cbLTSearchMultipleLOB": 654,
    "cbLTSearchMultipleOmnia": 655,
    "cbOCEPAlvariaID": 179,
    "cbOCEPBillability": 182,
    "cbOCEPBusUnit": 157,
    "cbOCEPCampaign": 158,
    "cbOCEPClient": 196,
    "cbOCEPCountry": 155,
    "cbOCEPEmpStatus": 188,
    "cbOCEPLOB": 165,
    "cbOCEPPosition": 173,
    "cbOCEPRole": 171,
    "cbOCEPSite": 163,
    "cbOCEPStatus": 181,
    "cbOCEPSubLOB": 174,
    "cbOCEPSubUnit": 166,
    "cbOCEPSupervisor": 189,
    "cbOCFPAlvariaID": 582,
    "cbOCFPBillability": 563,
    "cbOCFPBusUnit": 535,
    "cbOCFPClient": 550,
    "cbOCFPCountry": 576,
    "cbOCFPDivision": 554,
    "cbOCFPEmpStatus": 547,
    "cbOCFPLOB": 557,
    "cbOCFPPosition": 541,
    "cbOCFPRole": 579,
    "cbOCFPSite": 573,
    "cbOCFPStatus": 544,
    "cbOCFPSubLOB": 560,
    "cbOCFPSubUnit": 538,
    "cbOCFPSupervisor": 566,
    "cbOTBillability": 323,
    "cbOTBusUnit": 305,
    "cbOTClient": 317,
    "cbOTLOB": 358,
    "cbOTOmnia": 282,
    "cbOTPosition": 352,
    "cbOTSearchLOB": 284,
    "cbOTStatus": 308,
    "cbOTSub-LOB": 299,
    "cbOTSubUnit": 311,
    "cbOTSupervisor": 338,
    "cbOTSupervisorEmpID": 344,
    "cbPRMultipleBillability_1": 471,
    "cbPRMultipleBusUnit_1": 450,
    "cbPRMultipleClient_1": 462,
    "cbPRMultipleLOB_2": 465,
    "cbPRMultiplePosition_1": 456,
    "cbPRMultipleSub-LOB": 468,
    "cbPRMultipleSubUnit_1": 453,
    "cbPRMultipleSupervisor_1": 474,
    "cbPRMultipleSupervisorEmail_1": 482,
    "cbPRMultipleSupervisorEmpID_1": 477,
    "cbPRSearchMultipleLOB": 431,
    "cbPRSearchMultipleOmnia": 432,
    "CLASS NAME_Column1": 739,
    "class_name": 362,
    "Class_Name": 79,
    "CLASS_NAME": 363,
    "ClassName": 361,
    "CLIENT_Column1_1": 728,
    "CLIENT_DataCard PRMp1_1": 461,
    "CLIENT_LTMDataCard": 684,
    "CLIENT_LTMDataCard2": 622,
    "CLIENT_OTDataCard": 316,
    "CLIENT_OTDataCard1": 36,
    "CLIENT_PRMDataCard2_2": 399,
    "comment_card": 140,
    "comment_card_1": 273,
    "comment_input": 142,
    "comment_input_1": 275,
    "comment_label": 141,
    "comment_label_1": 274,
    "COUNTRY_Column1_1": 732,
    "Country_DataCard": 567,
    "Country_DataCard1": 574,
    "CS FreshService": 503,
    "CS FreshService Group": 508,
    "DataCard10": 583,
    "DataCard2": 548,
    "DataCard3": 564,
    "DataCard7": 619,
    "DataCard8": 552,
    "DataCardKey1": 605,
    "DataCardKey1_1": 16,
    "DataCardKey10": 524,
    "DataCardKey11": 530,
    "DataCardKey12": 705,
    "DataCardKey13": 327,
    "DataCardKey14": 333,
    "DataCardKey15": 346,
    "DataCardKey15_1": 537,
    "DataCardKey16": 479,
    "DataCardKey16_1": 540,
    "DataCardKey18": 46,
    "DataCardKey19": 52,
    "DataCardKey2": 689,
    "DataCardKey24": 667,
    "DataCardKey24_1": 296,
    "DataCardKey27": 28,
    "DataCardKey28": 34,
    "DataCardKey29": 40,
    "DataCardKey3": 466,
    "DataCardKey35": 559,
    "DataCardKey36": 614,
    "DataCardKey36_1": 31,
    "DataCardKey37": 674,
    "DataCardKey37_1": 611,
    "DataCardKey37_2": 306,
    "DataCardKey37_3": 25,
    "DataCardKey38": 677,
    "DataCardKey38_1": 312,
    "DataCardKey39": 686,
    "DataCardKey39_1": 318,
    "DataCardKey4": 626,
    "DataCardKey40": 695,
    "DataCardKey40_1": 324,
    "DataCardKey41": 680,
    "DataCardKey41_1": 353,
    "DataCardKey42": 698,
    "DataCardKey42_1": 339,
    "DataCardKey43_1": 330,
    "DataCardKey44": 617,
    "DataCardKey44_1": 70,
    "DataCardKey45": 623,
    "DataCardKey45_1": 37,
    "DataCardKey46": 556,
    "DataCardKey47": 670,
    "DataCardKey47_1": 608,
    "DataCardKey47_2": 302,
    "DataCardKey47_3": 22,
    "DataCardKey48": 562,
    "DataCardKey5": 359,
    "DataCardKey50": 633,
    "DataCardKey50_1": 43,
    "DataCardKey51_1": 49,
    "DataCardKey52_1": 58,
    "DataCardKey55": 578,
    "DataCardKey56": 515,
    "DataCardKey6": 518,
    "DataCardKey7": 76,
    "DataCardKey8": 403,
    "DataCardKey9": 521,
    "DataCardKeyBILLpm1_1": 472,
    "DataCardKeyBILLPRpm2_1": 410,
    "DataCardKeyBUpm1_1": 451,
    "DataCardKeyBUPRpm2_1": 388,
    "DataCardKeyCLpm1_1": 463,
    "DataCardKeyCLPRpm2_1": 400,
    "DataCardKeyENpm1_1": 444,
    "DataCardKeyENPRpm2_1": 382,
    "DataCardKeyPOSpm1_1": 457,
    "DataCardKeyPOSPRpm2_1": 394,
    "DataCardKeySITEpm1_1": 447,
    "DataCardKeySITEPRpm2_1": 385,
    "DataCardKeySUpm1_1": 454,
    "DataCardKeySUPpm1_1": 475,
    "DataCardKeySUPPRpm2_1": 413,
    "DataCardKeySUPRpm2_1": 391,
    "DataCardValue2": 628,
    "DataCardValue4": 405,
    "dateEnd": 320,
    "dateNesting": 326,
    "dateOCEPHireDate": 187,
    "dateOCFPHireDate": 531,
    "dateProduction": 332,
    "dateStart": 314,
    "dpLTEffectivityDate": 708,
    "dpPREffectivityDate": 485,
    "drpOTtimezone": 335,
    "drpRosterSelection": 498,
    "EFFECTIVITY_DATE": 484,
    "EFFECTIVITY_DATE_LT": 707,
    "EffectivityDate": 421,
    "effectivityDate_card": 131,
    "effectivityDate_card_1": 264,
    "effectivityDate_input": 133,
    "effectivityDate_input_1": 266,
    "effectivityDate_label": 132,
    "effectivityDate_label_1": 265,
    "EFFECTIVITYDATE_LT": 644,
    "email_card": 113,
    "email_card_1": 246,
    "email_label": 114,
    "email_label_1": 247,
    "email_value": 115,
    "email_value_1": 248,
    "EMPLOYEE ID_Column1_1": 721,
    "EMPLOYEE ID_DataCard1": 604,
    "EMPLOYEE ID_DataCardOCFP": 514,
    "EMPLOYEE ID_LTMDataCard": 666,
    "EMPLOYEE ID_OTDataCard": 295,
    "EMPLOYEE ID_OTDataCard1": 15,
    "EMPLOYEE NAME_PRMDataCard_3": 381,
    "EmployeeGallery": 94,
    "EmployeeGallery_1": 226,
    "employeeID_1": 231,
    "EmployeeInfo_form": 100,
    "EmployeeInfo_form_1": 233,
    "employeeInfo_label": 93,
    "employeeInfo_label_1": 225,
    "employeeList_label": 92,
    "employeeList_label_1": 224,
    "employeeName": 96,
    "employeeName_1": 228,
    "EMPLOYEESTATUS_DataCard12": 545,
    "EMPLOYMENT STATUS_Column1": 736,
    "END DATE_OTDataCard": 319,
    "END DATE_OTDataCard1": 39,
    "ErrorMessage1": 706,
    "ErrorMessage2": 347,
    "ErrorMessage3": 480,
    "FIRST NAME_Column1_1": 722,
    "FIRST NAME_DataCardOCFP": 517,
    "fname_card": 101,
    "fname_card_1": 234,
    "fname_label": 102,
    "fname_label_1": 235,
    "fname_value": 103,
    "fname_value_1": 236,
    "formLTM": 665,
    "formLTM2": 603,
    "formOCFirstPage1": 513,
    "formOCFirstPage2": 532,
    "formOCFirstPage3": 551,
    "formOCFirstPage4": 570,
    "formOT": 294,
    "formOT1": 14,
    "formPREDsp2": 442,
    "formPREDsp2_1": 380,
    "FULL NAME_DataCard PRMp1_1": 443,
    "galleryLTM": 659,
    "galleryLTM_1": 597,
    "galleryLTM_2": 8,
    "galleryOT": 288,
    "galleryPRMp1st_1": 436,
    "galleryPRMp2nd_1": 374,
    "galleryTemplate2": 660,
    "galleryTemplate2_1": 598,
    "galleryTemplate2_2": 289,
    "galleryTemplate2_3": 9,
    "galleryTemplate2_4": 437,
    "galleryTemplate2_5": 375,
    "galleryTemplate3": 95,
    "galleryTemplate3_1": 227,
    "galleryTemplate6": 150,
    "galOCEP": 149,
    "grpLTSearchMultipleLOB": 714,
    "grpLTSearchMultipleOmnia": 715,
    "grpNewOCForm": 591,
    "grpOCECountry": 201,
    "grpOCEPBillability": 198,
    "grpOCEPBusUnit": 212,
    "grpOCEPButtons": 221,
    "grpOCEPCampaign": 205,
    "grpOCEPClient": 204,
    "grpOCEPEmpId": 218,
    "grpOCEPEmpStatus": 216,
    "grpOCEPFName": 208,
    "grpOCEPHireDate": 211,
    "grpOCEPInternalEmail": 217,
    "grpOCEPLName": 210,
    "grpOCEPLOB": 206,
    "grpOCEPMName": 209,
    "grpOCEPPosition": 214,
    "grpOCEPRole": 203,
    "grpOCEPRole_1": 199,
    "grpOCEPSite": 202,
    "grpOCEPStatus": 215,
    "grpOCEPSubLOB": 207,
    "grpOCEPSubUnit": 213,
    "grpOCEPSupervisor": 200,
    "grpOCFPButtons": 592,
    "grpOCSPActions": 748,
    "grpOCSPButtons": 747,
    "grpOTLOB": 368,
    "grpOTOmnia": 369,
    "grpPRSearchMultipleLOB_1": 491,
    "grpPRSearchMultipleOmnia_1": 492,
    "HIRE DATE_Column1_1": 725,
    "HIRE DATE_DataCardOCFP": 529,
    "HomePage": 493,
    "Host": 3,
    "Image2": 504,
    "INTERNAL EMAIL": 526,
    "INTERNAL EMAIL_Column1": 737,
    "INTERNSHIP_DataCard": 458,
    "INTERNSHIP_LTMDataCard": 681,
    "INTERNSHIP_PRMDataCard_2": 396,
    "Label1": 260,
    "Label10": 356,
    "Label11": 397,
    "Label12": 398,
    "Label13": 682,
    "Label14": 81,
    "Label15": 621,
    "Label16": 620,
    "Label17": 61,
    "Label18": 336,
    "Label19": 495,
    "Label19_1": 499,
    "Label2": 309,
    "Label20": 55,
    "Label21": 56,
    "Label22": 553,
    "Label23": 496,
    "Label24": 572,
    "Label25": 534,
    "Label26": 67,
    "Label27": 543,
    "Label28": 73,
    "Label29": 546,
    "Label3": 315,
    "Label30": 62,
    "Label31": 74,
    "Label32": 80,
    "Label33": 68,
    "Label34": 645,
    "Label35": 646,
    "Label36": 636,
    "Label37": 527,
    "Label38": 637,
    "Label39": 486,
    "Label4": 321,
    "Label40": 422,
    "Label41": 423,
    "Label42": 505,
    "Label42_1": 506,
    "Label43": 191,
    "Label44": 483,
    "Label45": 701,
    "Label46": 416,
    "Label47": 417,
    "Label48": 639,
    "Label49": 640,
    "Label5": 152,
    "Label5_1": 159,
    "Label5_10": 192,
    "Label5_11": 154,
    "Label5_12": 162,
    "Label5_13": 169,
    "Label5_14": 186,
    "Label5_15": 151,
    "Label5_16": 160,
    "Label5_17": 167,
    "Label5_18": 178,
    "Label5_19": 175,
    "Label5_2": 168,
    "Label5_20": 193,
    "Label5_21": 183,
    "Label5_3": 176,
    "Label5_4": 184,
    "Label5_5": 153,
    "Label5_6": 161,
    "Label5_7": 170,
    "Label5_8": 185,
    "Label5_9": 177,
    "Label50": 549,
    "Label51": 565,
    "Label52": 568,
    "Label53": 581,
    "Label54": 586,
    "Label54_1": 194,
    "Label55": 692,
    "Label56": 630,
    "Label57": 631,
    "Label58": 469,
    "Label59": 575,
    "Label6": 709,
    "Label60": 408,
    "Label61": 300,
    "Label62": 19,
    "Label63": 20,
    "Label64": 584,
    "Label65": 642,
    "Label66": 643,
    "Label67": 64,
    "Label68": 65,
    "Label69": 419,
    "Label7": 459,
    "Label70": 420,
    "Label71": 120,
    "Label72": 360,
    "Label73": 123,
    "Label74": 77,
    "Label75": 253,
    "Label76": 254,
    "Label77": 256,
    "Label78": 257,
    "Label79": 404,
    "Label8": 342,
    "Label80": 627,
    "Label9": 350,
    "LAST NAME_Column1_1": 724,
    "LAST NAME_DataCardOCFP": 523,
    "lastDate_card": 134,
    "lastDate_card_1": 267,
    "lastDate_input": 136,
    "lastDate_input_1": 269,
    "lastDate_label": 135,
    "lastDate_label_1": 268,
    "Lateral Transfer Form_1": 652,
    "Lateral Transfer Form_2": 657,
    "Lateral Transfer Form_3": 658,
    "Lateral Transfer Form_4": 594,
    "Lateral Transfer Form_5": 595,
    "Lateral Transfer Form_6": 596,
    "LateralTransfer_FirstPage": 651,
    "LateralTransfer_SecondPage": 593,
    "LineOfBusiness_Label_1": 90,
    "lname_card": 104,
    "lname_card_1": 237,
    "lname_label": 105,
    "lname_label_1": 239,
    "lname_value": 106,
    "lname_value_1": 238,
    "lob_card": 110,
    "lob_card_1": 243,
    "LOB_Column1_1": 730,
    "LOB_DataCard1": 687,
    "LOB_DataCard2": 464,
    "LOB_DataCard3": 625,
    "LOB_DataCard4": 357,
    "LOB_DataCard7": 402,
    "LOB_DataCardOCFP": 555,
    "lob_input": 89,
    "lob_label": 111,
    "lob_Label": 88,
    "lob_label_1": 245,
    "LOB_OTDataCard1": 75,
    "lob_value": 112,
    "lob_value_1": 244,
    "MIDDLE NAME_Column1_1": 723,
    "MIDDLE NAME_DataCardOCFP": 520,
    "MultipleTerminationForm_Label": 87,
    "MultipleTerminationForm_Label_1": 223,
    "NESTING START DATE_DataCard1": 325,
    "NESTING START DATE_DataCard3": 45,
    "NewHireOnboarding_EditPage": 147,
    "NewHireOnboarding_FirstPage": 510,
    "NewHireOnboarding_SecondPage": 716,
    "NextArrow2": 662,
    "NextArrow2_1": 291,
    "NextArrow2_1_Verify_1": 439,
    "NextArrow3": 600,
    "NextArrow3_1": 11,
    "NextArrow4": 97,
    "NextArrow4_2": 229,
    "NextArrow4_2_Verify_1": 377,
    "oc1": 511,
    "oc2": 717,
    "oc3": 148,
    "omnia_input": 91,
    "omniaID": 98,
    "omniaID_1": 230,
    "OT1": 281,
    "OT2": 287,
    "OT3": 286,
    "OT4": 7,
    "OT5": 6,
    "OT6": 5,
    "Others_FirstPage": 280,
    "Others_SecondPage": 4,
    "position_card": 107,
    "position_card_1": 240,
    "POSITION_Column1_1": 727,
    "POSITION_DataCard PRMp1_1": 455,
    "POSITION_DataCardOCFP": 539,
    "position_label": 108,
    "position_label_1": 241,
    "POSITION_LTMDataCard": 678,
    "POSITION_LTMDataCard2": 616,
    "POSITION_OTDataCard": 351,
    "POSITION_OTDataCard1": 69,
    "POSITION_PRMDataCard2_2": 393,
    "position_value": 109,
    "position_value_1": 242,
    "proceed_btn": 146,
    "proceed_btn_1": 279,
    "PRODUCTION DATE_DataCard1": 331,
    "PRODUCTION DATE_DataCard3": 51,
    "Promotion Form p2_1": 371,
    "Promotion Form_1": 429,
    "Promotion_FirstPage": 428,
    "Promotion_SecondPage": 370,
    "Promotion-Sub_LOB2": 406,
    "Promotion-Sub_LOB2_Label": 407,
    "rdLTMInternship": 683,
    "rdPRInternship": 460,
    "Rectangle1": 512,
    "Rectangle2": 494,
    "Rectangle3": 501,
    "Rectangle3_1": 502,
    "REGULARIZATION DATE_Column1": 734,
    "Reminder": 507,
    "Remove Button Container": 276,
    "Remove_BTN": 647,
    "Remove_Button": 424,
    "REMOVE_BUTTON": 82,
    "ROLE_Column1_1": 733,
    "ROLE_DataCardOCFP": 577,
    "Roster Update Selection": 497,
    "Save Button Container": 143,
    "Save_Button": 364,
    "SAVE_BUTTON": 487,
    "SAVE_BUTTON_LT": 710,
    "SCHEDULE_OTDataCard": 328,
    "SCHEDULE_OTDataCard1": 48,
    "Separator2": 664,
    "Separator2_1": 293,
    "Separator2_1_Verify_1": 441,
    "Separator3": 602,
    "Separator3_1": 13,
    "Separator4": 99,
    "Separator4_2": 232,
    "Separator4_2_Verify_1": 379,
    "SITE DataCard PRMp1_1": 446,
    "SITE_Column1_1": 744,
    "Site_DataCard": 571,
    "SITE_LTMDataCard": 669,
    "SITE_LTMDataCard2": 607,
    "SITE_OTDataCard": 301,
    "SITE_OTDataCard1": 21,
    "SITE_PRMDataCard_4": 384,
    "START DATE_OTDataCard": 313,
    "START DATE_OTDataCard1": 33,
    "StarVisible1": 704,
    "StarVisible2": 345,
    "StarVisible3": 478,
    "STATUS_Column1": 735,
    "STATUS_DataCardOCFP": 542,
    "STATUS_OTDataCard": 307,
    "STATUS_OTDataCard1": 27,
    "Sub-LOB": 467,
    "SUB-LOB": 629,
    "SUB-LOB_Column1_1": 742,
    "Sub-LOB_DataCard": 690,
    "SUB-LOB_DataCardOCFP": 558,
    "SUB-LOB_OTDataCard": 298,
    "SUB-LOB2_OTDataCard": 18,
    "SUB-UNIT_Column1": 741,
    "SUB-UNIT_DataCard PRMp1_1": 452,
    "SUB-UNIT_DataCardOCFP": 536,
    "SUB-UNIT_LTMDataCard": 675,
    "SUB-UNIT_LTMDataCard2": 613,
    "SUB-UNIT_OTDataCard": 310,
    "SUB-UNIT_OTDataCard1": 30,
    "SUB-UNIT_PRMDataCard2_2": 390,
    "SUPERVISOR EMP ID": 641,
    "SUPERVISOR EMP ID_Column1": 740,
    "supervisor_card": 119,
    "supervisor_card_1": 252,
    "SUPERVISOR_Column1_1": 743,
    "SUPERVISOR_DataCard PRMp1_1": 473,
    "SUPERVISOR_EMAIL": 481,
    "SUPERVISOR_EMAIL_LT": 699,
    "supervisor_emp_id": 122,
    "SUPERVISOR_EMP_ID": 63,
    "SUPERVISOR_EMP_ID_PRMDataCard": 418,
    "SUPERVISOR_LT": 635,
    "SUPERVISOR_LTMDataCard": 696,
    "SUPERVISOR_OTDataCard": 337,
    "SUPERVISOR_OTDataCard1": 57,
    "supervisor_value": 121,
    "SupervisorEmail": 415,
    "supervisorEmpID_1": 255,
    "supervisorEmpID_value": 124,
    "SUPERVISORS_EMAIL_LT": 638,
    "tblOCSP": 720,
    "TEAM_PRMDataCard2_2": 412,
    "TEAMLEADEREMP.ID_DataCard1": 702,
    "TEAMLEADEREMP.ID_DataCard2": 343,
    "TEAMLEADEREMP.ID_DataCard3": 476,
    "Termination Status Verify": 263,
    "Termination_FirstPage": 86,
    "Termination_VerificationPage": 222,
    "terminationStatus_card": 128,
    "terminationStatus_card_1": 261,
    "terminationStatus_cb": 130,
    "terminationStatus_label": 129,
    "terminationStatus_label_1": 262,
    "terminationType_card": 125,
    "terminationType_card_1": 258,
    "terminationType_cb": 127,
    "terminationType_label": 126,
    "terminationType_label_1": 259,
    "Time_Zone": 334,
    "TIME_ZONE": 54,
    "trainer1": 341,
    "Trainer1": 60,
    "TRAINER1": 340,
    "trainer2": 349,
    "Trainer2": 66,
    "TRAINER2": 348,
    "trainer3": 355,
    "Trainer3": 72,
    "TRAINER3": 354,
    "Treehouse Guide Group": 509,
    "txtLTMultipleBillability2": 634,
    "txtLTMultipleBusUnit2": 612,
    "txtLTMultipleEmpId": 668,
    "txtLTMultipleEmpId2": 606,
    "txtLTMultipleName": 661,
    "txtLTMultipleName_1": 599,
    "txtLTMultipleName_2": 10,
    "txtLTMultipleName_3": 376,
    "txtLTMultipleOmnia": 663,
    "txtLTMultipleOmnia_1": 601,
    "txtLTMultipleOmnia_2": 12,
    "txtLTMultiplePosition2": 618,
    "txtLTMultipleSite": 671,
    "txtLTMultipleSite2": 609,
    "txtLTMultipleSubUnit2": 615,
    "txtLTMutipleClient2": 624,
    "txtLTSearchMultipleLOB": 653,
    "txtLTSearchMultipleOmnia": 656,
    "txtOCEPClassName": 190,
    "txtOCEPEmpId": 156,
    "txtOCEPFName": 164,
    "txtOCEPInternalEmail": 195,
    "txtOCEPLName": 180,
    "txtOCEPMName": 172,
    "txtOCEPSupervisorEmpID": 197,
    "txtOCFPClassName": 585,
    "txtOCFPEmpId": 516,
    "txtOCFPFName": 519,
    "txtOCFPLName": 525,
    "txtOCFPMName": 522,
    "txtOCFPSupervisorEmpId": 569,
    "txtOCInternalEmail": 528,
    "txtOTBillability1": 44,
    "txtOTBusUnit1": 26,
    "txtOTClient1": 38,
    "txtOTEmpId": 297,
    "txtOTEmpId1": 17,
    "txtOTEndDate1": 41,
    "txtOTLOB": 283,
    "txtOTLOB1": 78,
    "txtOTMName": 290,
    "txtOTMOmnia": 292,
    "txtOTNesting1": 47,
    "txtOTOmnia": 285,
    "txtOTPosition1": 71,
    "txtOTProduction1": 53,
    "txtOTSchedule": 329,
    "txtOTSchedule1": 50,
    "txtOTSite": 303,
    "txtOTSite1": 23,
    "txtOTStartdate1": 35,
    "txtOTStatus1": 29,
    "txtOTSubUnit1": 32,
    "txtOTSupervisor1": 59,
    "txtPREDp1_1": 435,
    "txtPREDp2_1": 373,
    "txtPRMultipleBILLpm2_1": 411,
    "txtPRMultipleBUpm2_1": 389,
    "txtPRMultipleCLpm2_1": 401,
    "txtPRMultipleEmpName_1": 445,
    "txtPRMultipleEmpNamepm2_1": 383,
    "txtPRMultipleNamepm1_1": 438,
    "txtPRMultipleOmniapm1": 440,
    "txtPRMultipleOmniapm2_1": 378,
    "txtPRMultiplePOSpm2_1": 395,
    "txtPRMultipleSite_1": 448,
    "txtPRMultipleSitepm2_1": 386,
    "txtPRMultipleSUpm2_1": 392,
    "txtPRMultipleSUPpm2_1": 414,
    "txtPRSearchMultipleLOB_1": 430,
    "txtPRSearchMultipleOmnia_1": 433,
    "txtPRSEp1_1": 434,
    "txtPRUEp2_1": 372
  },
  "FunctionParamsInvariantScripts": {},
  "FunctionParamsInvariantScriptsOnInstances": {},
  "HeaderLastSavedDateTimeUTC": "07/06/2024 16:38:03",
  "IsLegacyComponentAllowGlobalScopeCase": false,
  "LocalConnectionIDReferences": {
    "008b4f93-a63b-49d3-9958-6dbd0fbb748d": "\"/providers/microsoft.powerapps/apis/shared_logicflows/connections/c04e8e8e-cc0f-4a81-a3e3-77c930025dc4\"",
    "445c2806-6ace-410f-adcf-5edfa6f6c6cb": "\"/providers/microsoft.powerapps/apis/shared_excelonlinebusiness/connections/e8057648d5254ded85eabac86900a71e\"",
    "64340f7a-1f9b-4f42-94b5-d7af11dd8dde": "\"/providers/microsoft.powerapps/apis/shared_logicflows/connections/8d71eb372a62403e910a072ebf0f00f4-f1c323350ee50a3a\"",
    "6cc33adf-69fa-4baa-8c79-ea529c655339": "\"/providers/microsoft.powerapps/apis/shared_logicflows/connections/110487544e584ab0ab425a0db8a96338-f1c323350ee50a3a\"",
    "77168477-7f8b-4be7-bf7b-e48ba083da0c": "\"/providers/microsoft.powerapps/apis/shared_logicflows/connections/d718e933082e42fca3b53c1125ff80df-f1c323350ee50a3a\"",
    "9d2cc37f-5727-4e34-938a-04ab2e1962fb": "\"/providers/microsoft.powerapps/apis/shared_logicflows/connections/6937b00b47884d508f52051066369d1e-f1c323350ee50a3a\"",
    "a98f1ce0-65af-4442-ad24-7697c24f3724": "\"/providers/microsoft.powerapps/apis/shared_office365/connections/62bfa946d73f4bf1b4c5d4b4c842edfb\"",
    "f001c07c-733c-47b5-9cc0-afa32cdc09de": "\"/providers/microsoft.powerapps/apis/shared_sharepointonline/connections/9a1322d96bcf422b8b9c4a9d917e14d4\""
  },
  "LocalDatabaseReferencesAsEmpty": true,
  "LocalResourceFileNames": {
    "bit.ly_CSFreshService": "4899ac47-87d7-40f1-9936-d68396123f4c.png",
    "bit.ly_DynamicRosterUpdateApplication-Treehouse": "9067cb6b-839b-4058-95bd-2eb00d298c02.png",
    "homeScreen": "83ae0a84-050f-4954-af53-4824d9d7e624.png",
    "homeScreen2": "f3221eef-2964-4bea-bdec-75bd42bdf521.png",
    "MicrosoftTeams-image": "7886b3c1-9983-4892-a2e5-cec6afa3fa41.png",
    "MicrosoftTeams-image (2)": "f781a3c3-d213-4099-acf4-9844bd2d1c6a.png",
    "Untitled design 29": "978392d2-fc92-4e8f-a15e-6aa4c499d7d4.png"
  },
  "LocalResourceRootPaths": {
    "bit.ly_CSFreshService": "https://docserverpwaprodeus.blob.core.windows.net/eae66d51-2f22-42c0-93b3-0e21961f6d20-1/resource/Assets0Images04899ac47-87d7-40f1-9936-d68396123f4c.png?skoid=58690ece-ec83-4ce2-9ce8-883d4d6a54ee&sktid=975f013f-7f24-47e8-a7d3-abc4752bf346&skt=2024-07-06T16%3A34%3A34Z&ske=2024-07-07T16%3A49%3A34Z&sks=b&skv=2023-01-03&sv=2023-01-03&spr=https&se=2024-07-07T16%3A49%3A34Z&sr=b&sp=r&sig=PSWSXard7GIir0CXEAre0bmwjkaiCcG5qcnCuJ0ajIk%3D",
    "bit.ly_DynamicRosterUpdateApplication-Treehouse": "https://docserverpwaprodeus.blob.core.windows.net/eae66d51-2f22-42c0-93b3-0e21961f6d20-1/resource/Assets0Images09067cb6b-839b-4058-95bd-2eb00d298c02.png?skoid=58690ece-ec83-4ce2-9ce8-883d4d6a54ee&sktid=975f013f-7f24-47e8-a7d3-abc4752bf346&skt=2024-07-06T16%3A34%3A34Z&ske=2024-07-07T16%3A49%3A34Z&sks=b&skv=2023-01-03&sv=2023-01-03&spr=https&se=2024-07-07T16%3A49%3A34Z&sr=b&sp=r&sig=JikBpgZGARB9DOxPxrsrVY6drR5DJOjdikKvxpWsEsU%3D",
    "homeScreen": "https://docserverpwaprodeus.blob.core.windows.net/eae66d51-2f22-42c0-93b3-0e21961f6d20-1/resource/Assets0Images083ae0a84-050f-4954-af53-4824d9d7e624.png?skoid=58690ece-ec83-4ce2-9ce8-883d4d6a54ee&sktid=975f013f-7f24-47e8-a7d3-abc4752bf346&skt=2024-07-06T16%3A34%3A34Z&ske=2024-07-07T16%3A49%3A34Z&sks=b&skv=2023-01-03&sv=2023-01-03&spr=https&se=2024-07-07T16%3A49%3A34Z&sr=b&sp=r&sig=xrP4wX0AASG2e9Zz2Wlb8Xmo%2FshME64BkIlX5t8RA44%3D",
    "homeScreen2": "https://docserverpwaprodeus.blob.core.windows.net/eae66d51-2f22-42c0-93b3-0e21961f6d20-1/resource/Assets0Images0f3221eef-2964-4bea-bdec-75bd42bdf521.png?skoid=58690ece-ec83-4ce2-9ce8-883d4d6a54ee&sktid=975f013f-7f24-47e8-a7d3-abc4752bf346&skt=2024-07-06T16%3A34%3A34Z&ske=2024-07-07T16%3A49%3A34Z&sks=b&skv=2023-01-03&sv=2023-01-03&spr=https&se=2024-07-07T16%3A49%3A34Z&sr=b&sp=r&sig=t4xo9gjoGqS3iYJuTb%2Fly2vxTDVr9qQlgrzfYRMtdQE%3D",
    "MicrosoftTeams-image": "https://docserverpwaprodeus.blob.core.windows.net/eae66d51-2f22-42c0-93b3-0e21961f6d20-1/resource/Assets0Images07886b3c1-9983-4892-a2e5-cec6afa3fa41.png?skoid=58690ece-ec83-4ce2-9ce8-883d4d6a54ee&sktid=975f013f-7f24-47e8-a7d3-abc4752bf346&skt=2024-07-06T16%3A34%3A34Z&ske=2024-07-07T16%3A49%3A34Z&sks=b&skv=2023-01-03&sv=2023-01-03&spr=https&se=2024-07-07T16%3A49%3A34Z&sr=b&sp=r&sig=mGaB4G1mW9uq0%2FF6FWmkwV43OgqzSXZdHvrk6UK2ldY%3D",
    "MicrosoftTeams-image (2)": "https://docserverpwaprodeus.blob.core.windows.net/eae66d51-2f22-42c0-93b3-0e21961f6d20-1/resource/Assets0Images0f781a3c3-d213-4099-acf4-9844bd2d1c6a.png?skoid=58690ece-ec83-4ce2-9ce8-883d4d6a54ee&sktid=975f013f-7f24-47e8-a7d3-abc4752bf346&skt=2024-07-06T16%3A34%3A34Z&ske=2024-07-07T16%3A49%3A34Z&sks=b&skv=2023-01-03&sv=2023-01-03&spr=https&se=2024-07-07T16%3A49%3A34Z&sr=b&sp=r&sig=etO4rh81VMBakXhKleKDmSgYCm7DLMYeKl4vuDBoha4%3D",
    "Untitled design 29": "https://docserverpwaprodeus.blob.core.windows.net/eae66d51-2f22-42c0-93b3-0e21961f6d20-1/resource/Assets0Images0978392d2-fc92-4e8f-a15e-6aa4c499d7d4.png?skoid=58690ece-ec83-4ce2-9ce8-883d4d6a54ee&sktid=975f013f-7f24-47e8-a7d3-abc4752bf346&skt=2024-07-06T16%3A34%3A34Z&ske=2024-07-07T16%3A49%3A34Z&sks=b&skv=2023-01-03&sv=2023-01-03&spr=https&se=2024-07-07T16%3A49%3A34Z&sr=b&sp=r&sig=RTOLuH2lZgUO3shiwzA1I%2Brk26rDeFfWHiCQg%2Btckmw%3D"
  },
  "OldLogoFileName": "mlxmmrgs.jpg",
  "OrderComponentMetadata": {},
  "OrderComponentTemplate": {},
  "OrderDataSource": {
    "colLateralTransfer": 11,
    "colOldLOB": 16,
    "colOmniaCreation": 15,
    "colOROldLOB": 19,
    "colOthers": 12,
    "colPROldLOB": 18,
    "colPromotion": 14,
    "colTROldLOB": 17,
    "ComboBoxSample": 6,
    "CustomGallerySample": 7,
    "DropDownSample": 8,
    "Headcount_table": 10,
    "Office365Outlook": 0,
    "PROD-Lateral_Transfer": 3,
    "PROD-New_Hire_Onboarding": 5,
    "PROD-Other_Roster_Update": 2,
    "PROD-Promotion": 1,
    "PROD-Termination": 4,
    "RadioSample": 9,
    "userVerify": 13
  },
  "OrderGroupControls": {
    "CS FreshService Group": {
      "CS FreshService": 1,
      "Label42": 0,
      "Rectangle3": 2
    },
    "grpLTSearchMultipleLOB": {
      "cbLTSearchMultipleLOB": 1,
      "txtLTSearchMultipleLOB": 0
    },
    "grpLTSearchMultipleOmnia": {
      "cbLTSearchMultipleOmnia": 0,
      "txtLTSearchMultipleOmnia": 1
    },
    "grpNewOCForm": {
      "formOCFirstPage1": 3,
      "formOCFirstPage2": 2,
      "formOCFirstPage3": 1,
      "formOCFirstPage4": 0
    },
    "grpOCECountry": {
      "cbOCEPCountry": 0,
      "Label5_15": 1
    },
    "grpOCEPBillability": {
      "cbOCEPBillability": 1,
      "Label5_18": 0
    },
    "grpOCEPBusUnit": {
      "cbOCEPBusUnit": 0,
      "Label5_5": 1
    },
    "grpOCEPButtons": {
      "btnOCEPBack": 0,
      "btnOCEPUpdate": 1
    },
    "grpOCEPCampaign": {
      "cbOCEPCampaign": 0,
      "Label5_11": 1
    },
    "grpOCEPClient": {
      "cbOCEPClient": 0,
      "Label5_10": 1
    },
    "grpOCEPEmpId": {
      "Label5": 1,
      "txtOCEPEmpId": 0
    },
    "grpOCEPEmpStatus": {
      "cbOCEPEmpStatus": 1,
      "Label5_8": 0
    },
    "grpOCEPFName": {
      "Label5_1": 1,
      "txtOCEPFName": 0
    },
    "grpOCEPHireDate": {
      "dateOCEPHireDate": 1,
      "Label5_4": 0
    },
    "grpOCEPInternalEmail": {
      "Label43": 0,
      "txtOCEPInternalEmail": 1
    },
    "grpOCEPLName": {
      "Label5_3": 0,
      "txtOCEPLName": 1
    },
    "grpOCEPLOB": {
      "cbOCEPLOB": 0,
      "Label5_12": 1
    },
    "grpOCEPMName": {
      "Label5_2": 0,
      "txtOCEPMName": 1
    },
    "grpOCEPPosition": {
      "cbOCEPPosition": 0,
      "Label5_7": 1
    },
    "grpOCEPRole": {
      "cbOCEPRole": 1,
      "Label5_17": 0
    },
    "grpOCEPRole_1": {
      "cbOCEPAlvariaID": 1,
      "Label5_19": 0
    },
    "grpOCEPSite": {
      "cbOCEPSite": 0,
      "Label5_16": 1
    },
    "grpOCEPStatus": {
      "cbOCEPStatus": 0,
      "Label5_9": 1
    },
    "grpOCEPSubLOB": {
      "cbOCEPSubLOB": 1,
      "Label5_13": 0
    },
    "grpOCEPSubUnit": {
      "cbOCEPSubUnit": 0,
      "Label5_6": 1
    },
    "grpOCEPSupervisor": {
      "cbOCEPSupervisor": 0,
      "Label5_14": 1
    },
    "grpOCFPButtons": {
      "btnOCFPBack": 0,
      "btnOCFPReview": 1
    },
    "grpOCSPActions": {
      "btnOCSPEdit": 0,
      "btnOCSPRemove": 1
    },
    "grpOCSPButtons": {
      "btnOCSPBack": 0,
      "btnOCSPSubmit": 1
    },
    "grpOTLOB": {
      "cbOTSearchLOB": 1,
      "txtOTLOB": 0
    },
    "grpOTOmnia": {
      "cbOTOmnia": 0,
      "txtOTOmnia": 1
    },
    "grpPRSearchMultipleLOB_1": {
      "cbPRSearchMultipleLOB": 1,
      "txtPRSearchMultipleLOB_1": 0
    },
    "grpPRSearchMultipleOmnia_1": {
      "cbPRSearchMultipleOmnia": 0,
      "txtPRSearchMultipleOmnia_1": 1
    },
    "Reminder": {
      "Label19": 0,
      "Label23": 1,
      "Rectangle2": 2
    },
    "Treehouse Guide Group": {
      "Image2": 2,
      "Label42_1": 0,
      "Rectangle3_1": 1
    }
  },
  "OrderPcfTemplate": {},
  "OrderTemplate": {},
  "OrderXMLTemplate": {
    "button": 5,
    "combobox": 6,
    "datepicker": 9,
    "dropdown": 8,
    "form": 4,
    "gallery": 1,
    "htmlViewer": 7,
    "icon": 2,
    "image": 12,
    "label": 0,
    "radio": 11,
    "rectangle": 3,
    "text": 10
  },
  "OverridablePropertiesEntry": {
    "address_card": {},
    "address_card_1": {},
    "address_input": {},
    "address_input_1": {},
    "address_label": {},
    "address_label_1": {},
    "ALVARIA ID_Column1": {},
    "Alvaria_ID": {},
    "App": {},
    "BILLABILITY_Column1_1": {},
    "BILLABILITY_DataCard PRMp1_1": {},
    "BILLABILITY_DataCardOCFP": {},
    "BILLABILITY_LTMDataCard": {},
    "BILLABILITY_LTMDataCard2": {},
    "BILLABILITY_OTDataCard": {},
    "BILLABILITY_OTDataCard1": {},
    "BILLABILITY_PRMDataCard2_2": {},
    "btnFirstPageNext": {},
    "btnLTMultipleBack": {},
    "btnLTMultipleBack_1": {},
    "btnLTMultipleBack_2": {},
    "btnLTMultipleBack_3": {},
    "btnLTMultipleBack_4": {},
    "btnLTMultipleReview": {},
    "btnLTMultipleReview_1": {},
    "btnLTMultipleReview_2": {},
    "btnLTRemove": {},
    "btnLTRemove_1": {},
    "btnOCEPBack": {},
    "btnOCEPUpdate": {},
    "btnOCFPBack": {},
    "btnOCFPReview": {},
    "btnOCFPSave": {},
    "btnOCSPBack": {},
    "btnOCSPEdit": {},
    "btnOCSPRemove": {},
    "btnOCSPSubmit": {},
    "btnOTBack": {},
    "btnOTRemove": {},
    "btnOTReview": {},
    "btnOTSave": {},
    "btnPRMultipleBackp1_1": {},
    "btnPRMultipleBackp2_1": {},
    "btnPRMultipleReviewp1_1": {},
    "btnPRMultipleSubmitp2_1": {},
    "btnPRRemovep2_3": {},
    "BUSINESS UNIT_Column1_1": {},
    "BUSINESS UNIT_DataCard PRMp1_1": {},
    "BUSINESS UNIT_DataCardOCFP": {},
    "BUSINESS UNIT_LTMDataCard": {},
    "BUSINESS UNIT_LTMDataCard2": {},
    "BUSINESS UNIT_OTDataCard": {},
    "BUSINESS UNIT_OTDataCard1": {},
    "BUSINESS UNIT_PRMDataCard_4": {},
    "Button1": {},
    "Button2": {},
    "Button5": {},
    "Button6": {},
    "campaign_card": {},
    "campaign_card_1": {},
    "CAMPAIGN_Column1_1": {},
    "campaign_label": {},
    "campaign_label_1": {},
    "campaign_value": {},
    "campaign_value_1": {},
    "cbLTMultipleBillability": {},
    "cbLTMultipleBusUnit": {},
    "cbLTMultipleClient": {},
    "cbLTMultipleLOB": {},
    "cbLTMultiplePosition": {},
    "cbLTMultipleSubLOB": {},
    "cbLTMultipleSubUnit": {},
    "cbLTMultipleSupervisor": {},
    "cbLTMultipleSupervisorEmail_1": {},
    "cbLTMultipleSupervisorEmpID_1": {},
    "cbLTSearchMultipleLOB": {},
    "cbLTSearchMultipleOmnia": {},
    "cbOCEPAlvariaID": {},
    "cbOCEPBillability": {},
    "cbOCEPBusUnit": {},
    "cbOCEPCampaign": {},
    "cbOCEPClient": {},
    "cbOCEPCountry": {},
    "cbOCEPEmpStatus": {},
    "cbOCEPLOB": {},
    "cbOCEPPosition": {},
    "cbOCEPRole": {},
    "cbOCEPSite": {},
    "cbOCEPStatus": {},
    "cbOCEPSubLOB": {},
    "cbOCEPSubUnit": {},
    "cbOCEPSupervisor": {},
    "cbOCFPAlvariaID": {},
    "cbOCFPBillability": {},
    "cbOCFPBusUnit": {},
    "cbOCFPClient": {},
    "cbOCFPCountry": {},
    "cbOCFPDivision": {},
    "cbOCFPEmpStatus": {},
    "cbOCFPLOB": {},
    "cbOCFPPosition": {},
    "cbOCFPRole": {},
    "cbOCFPSite": {},
    "cbOCFPStatus": {},
    "cbOCFPSubLOB": {},
    "cbOCFPSubUnit": {},
    "cbOCFPSupervisor": {},
    "cbOTBillability": {},
    "cbOTBusUnit": {},
    "cbOTClient": {},
    "cbOTLOB": {},
    "cbOTOmnia": {},
    "cbOTPosition": {},
    "cbOTSearchLOB": {},
    "cbOTStatus": {},
    "cbOTSub-LOB": {},
    "cbOTSubUnit": {},
    "cbOTSupervisor": {},
    "cbOTSupervisorEmpID": {},
    "cbPRMultipleBillability_1": {},
    "cbPRMultipleBusUnit_1": {},
    "cbPRMultipleClient_1": {},
    "cbPRMultipleLOB_2": {},
    "cbPRMultiplePosition_1": {},
    "cbPRMultipleSub-LOB": {},
    "cbPRMultipleSubUnit_1": {},
    "cbPRMultipleSupervisor_1": {},
    "cbPRMultipleSupervisorEmail_1": {},
    "cbPRMultipleSupervisorEmpID_1": {},
    "cbPRSearchMultipleLOB": {},
    "cbPRSearchMultipleOmnia": {},
    "CLASS NAME_Column1": {},
    "class_name": {},
    "Class_Name": {},
    "CLASS_NAME": {},
    "ClassName": {},
    "CLIENT_Column1_1": {},
    "CLIENT_DataCard PRMp1_1": {},
    "CLIENT_LTMDataCard": {},
    "CLIENT_LTMDataCard2": {},
    "CLIENT_OTDataCard": {},
    "CLIENT_OTDataCard1": {},
    "CLIENT_PRMDataCard2_2": {},
    "comment_card": {},
    "comment_card_1": {},
    "comment_input": {},
    "comment_input_1": {},
    "comment_label": {},
    "comment_label_1": {},
    "COUNTRY_Column1_1": {},
    "Country_DataCard": {},
    "Country_DataCard1": {},
    "CS FreshService": {},
    "CS FreshService Group": {},
    "DataCard10": {},
    "DataCard2": {},
    "DataCard3": {},
    "DataCard7": {},
    "DataCard8": {},
    "DataCardKey1": {},
    "DataCardKey1_1": {},
    "DataCardKey10": {},
    "DataCardKey11": {},
    "DataCardKey12": {},
    "DataCardKey13": {},
    "DataCardKey14": {},
    "DataCardKey15": {},
    "DataCardKey15_1": {},
    "DataCardKey16": {},
    "DataCardKey16_1": {},
    "DataCardKey18": {},
    "DataCardKey19": {},
    "DataCardKey2": {},
    "DataCardKey24": {},
    "DataCardKey24_1": {},
    "DataCardKey27": {},
    "DataCardKey28": {},
    "DataCardKey29": {},
    "DataCardKey3": {},
    "DataCardKey35": {},
    "DataCardKey36": {},
    "DataCardKey36_1": {},
    "DataCardKey37": {},
    "DataCardKey37_1": {},
    "DataCardKey37_2": {},
    "DataCardKey37_3": {},
    "DataCardKey38": {},
    "DataCardKey38_1": {},
    "DataCardKey39": {},
    "DataCardKey39_1": {},
    "DataCardKey4": {},
    "DataCardKey40": {},
    "DataCardKey40_1": {},
    "DataCardKey41": {},
    "DataCardKey41_1": {},
    "DataCardKey42": {},
    "DataCardKey42_1": {},
    "DataCardKey43_1": {},
    "DataCardKey44": {},
    "DataCardKey44_1": {},
    "DataCardKey45": {},
    "DataCardKey45_1": {},
    "DataCardKey46": {},
    "DataCardKey47": {},
    "DataCardKey47_1": {},
    "DataCardKey47_2": {},
    "DataCardKey47_3": {},
    "DataCardKey48": {},
    "DataCardKey5": {},
    "DataCardKey50": {},
    "DataCardKey50_1": {},
    "DataCardKey51_1": {},
    "DataCardKey52_1": {},
    "DataCardKey55": {},
    "DataCardKey56": {},
    "DataCardKey6": {},
    "DataCardKey7": {},
    "DataCardKey8": {},
    "DataCardKey9": {},
    "DataCardKeyBILLpm1_1": {},
    "DataCardKeyBILLPRpm2_1": {},
    "DataCardKeyBUpm1_1": {},
    "DataCardKeyBUPRpm2_1": {},
    "DataCardKeyCLpm1_1": {},
    "DataCardKeyCLPRpm2_1": {},
    "DataCardKeyENpm1_1": {},
    "DataCardKeyENPRpm2_1": {},
    "DataCardKeyPOSpm1_1": {},
    "DataCardKeyPOSPRpm2_1": {},
    "DataCardKeySITEpm1_1": {},
    "DataCardKeySITEPRpm2_1": {},
    "DataCardKeySUpm1_1": {},
    "DataCardKeySUPpm1_1": {},
    "DataCardKeySUPPRpm2_1": {},
    "DataCardKeySUPRpm2_1": {},
    "DataCardValue2": {},
    "DataCardValue4": {},
    "dateEnd": {},
    "dateNesting": {},
    "dateOCEPHireDate": {},
    "dateOCFPHireDate": {},
    "dateProduction": {},
    "dateStart": {},
    "dpLTEffectivityDate": {},
    "dpPREffectivityDate": {},
    "drpOTtimezone": {},
    "drpRosterSelection": {},
    "EFFECTIVITY_DATE": {},
    "EFFECTIVITY_DATE_LT": {},
    "EffectivityDate": {},
    "effectivityDate_card": {},
    "effectivityDate_card_1": {},
    "effectivityDate_input": {},
    "effectivityDate_input_1": {},
    "effectivityDate_label": {},
    "effectivityDate_label_1": {},
    "EFFECTIVITYDATE_LT": {},
    "email_card": {},
    "email_card_1": {},
    "email_label": {},
    "email_label_1": {},
    "email_value": {},
    "email_value_1": {},
    "EMPLOYEE ID_Column1_1": {},
    "EMPLOYEE ID_DataCard1": {},
    "EMPLOYEE ID_DataCardOCFP": {},
    "EMPLOYEE ID_LTMDataCard": {},
    "EMPLOYEE ID_OTDataCard": {},
    "EMPLOYEE ID_OTDataCard1": {},
    "EMPLOYEE NAME_PRMDataCard_3": {},
    "EmployeeGallery": {},
    "EmployeeGallery_1": {},
    "employeeID_1": {},
    "EmployeeInfo_form": {},
    "EmployeeInfo_form_1": {},
    "employeeInfo_label": {},
    "employeeInfo_label_1": {},
    "employeeList_label": {},
    "employeeList_label_1": {},
    "employeeName": {},
    "employeeName_1": {},
    "EMPLOYEESTATUS_DataCard12": {},
    "EMPLOYMENT STATUS_Column1": {},
    "END DATE_OTDataCard": {},
    "END DATE_OTDataCard1": {},
    "ErrorMessage1": {},
    "ErrorMessage2": {},
    "ErrorMessage3": {},
    "FIRST NAME_Column1_1": {},
    "FIRST NAME_DataCardOCFP": {},
    "fname_card": {},
    "fname_card_1": {},
    "fname_label": {},
    "fname_label_1": {},
    "fname_value": {},
    "fname_value_1": {},
    "formLTM": {},
    "formLTM2": {},
    "formOCFirstPage1": {},
    "formOCFirstPage2": {},
    "formOCFirstPage3": {},
    "formOCFirstPage4": {},
    "formOT": {},
    "formOT1": {},
    "formPREDsp2": {},
    "formPREDsp2_1": {},
    "FULL NAME_DataCard PRMp1_1": {},
    "galleryLTM": {},
    "galleryLTM_1": {},
    "galleryLTM_2": {},
    "galleryOT": {},
    "galleryPRMp1st_1": {},
    "galleryPRMp2nd_1": {},
    "galleryTemplate2": {},
    "galleryTemplate2_1": {},
    "galleryTemplate2_2": {},
    "galleryTemplate2_3": {},
    "galleryTemplate2_4": {},
    "galleryTemplate2_5": {},
    "galleryTemplate3": {},
    "galleryTemplate3_1": {},
    "galleryTemplate6": {},
    "galOCEP": {},
    "grpLTSearchMultipleLOB": {},
    "grpLTSearchMultipleOmnia": {},
    "grpNewOCForm": {},
    "grpOCECountry": {},
    "grpOCEPBillability": {},
    "grpOCEPBusUnit": {},
    "grpOCEPButtons": {},
    "grpOCEPCampaign": {},
    "grpOCEPClient": {},
    "grpOCEPEmpId": {},
    "grpOCEPEmpStatus": {},
    "grpOCEPFName": {},
    "grpOCEPHireDate": {},
    "grpOCEPInternalEmail": {},
    "grpOCEPLName": {},
    "grpOCEPLOB": {},
    "grpOCEPMName": {},
    "grpOCEPPosition": {},
    "grpOCEPRole": {},
    "grpOCEPRole_1": {},
    "grpOCEPSite": {},
    "grpOCEPStatus": {},
    "grpOCEPSubLOB": {},
    "grpOCEPSubUnit": {},
    "grpOCEPSupervisor": {},
    "grpOCFPButtons": {},
    "grpOCSPActions": {},
    "grpOCSPButtons": {},
    "grpOTLOB": {},
    "grpOTOmnia": {},
    "grpPRSearchMultipleLOB_1": {},
    "grpPRSearchMultipleOmnia_1": {},
    "HIRE DATE_Column1_1": {},
    "HIRE DATE_DataCardOCFP": {},
    "HomePage": {},
    "Host": {},
    "Image2": {},
    "INTERNAL EMAIL": {},
    "INTERNAL EMAIL_Column1": {},
    "INTERNSHIP_DataCard": {},
    "INTERNSHIP_LTMDataCard": {},
    "INTERNSHIP_PRMDataCard_2": {},
    "Label1": {},
    "Label10": {},
    "Label11": {},
    "Label12": {},
    "Label13": {},
    "Label14": {},
    "Label15": {},
    "Label16": {},
    "Label17": {},
    "Label18": {},
    "Label19": {},
    "Label19_1": {},
    "Label2": {},
    "Label20": {},
    "Label21": {},
    "Label22": {},
    "Label23": {},
    "Label24": {},
    "Label25": {},
    "Label26": {},
    "Label27": {},
    "Label28": {},
    "Label29": {},
    "Label3": {},
    "Label30": {},
    "Label31": {},
    "Label32": {},
    "Label33": {},
    "Label34": {},
    "Label35": {},
    "Label36": {},
    "Label37": {},
    "Label38": {},
    "Label39": {},
    "Label4": {},
    "Label40": {},
    "Label41": {},
    "Label42": {},
    "Label42_1": {},
    "Label43": {},
    "Label44": {},
    "Label45": {},
    "Label46": {},
    "Label47": {},
    "Label48": {},
    "Label49": {},
    "Label5": {},
    "Label5_1": {},
    "Label5_10": {},
    "Label5_11": {},
    "Label5_12": {},
    "Label5_13": {},
    "Label5_14": {},
    "Label5_15": {},
    "Label5_16": {},
    "Label5_17": {},
    "Label5_18": {},
    "Label5_19": {},
    "Label5_2": {},
    "Label5_20": {},
    "Label5_21": {},
    "Label5_3": {},
    "Label5_4": {},
    "Label5_5": {},
    "Label5_6": {},
    "Label5_7": {},
    "Label5_8": {},
    "Label5_9": {},
    "Label50": {},
    "Label51": {},
    "Label52": {},
    "Label53": {},
    "Label54": {},
    "Label54_1": {},
    "Label55": {},
    "Label56": {},
    "Label57": {},
    "Label58": {},
    "Label59": {},
    "Label6": {},
    "Label60": {},
    "Label61": {},
    "Label62": {},
    "Label63": {},
    "Label64": {},
    "Label65": {},
    "Label66": {},
    "Label67": {},
    "Label68": {},
    "Label69": {},
    "Label7": {},
    "Label70": {},
    "Label71": {},
    "Label72": {},
    "Label73": {},
    "Label74": {},
    "Label75": {},
    "Label76": {},
    "Label77": {},
    "Label78": {},
    "Label79": {},
    "Label8": {},
    "Label80": {},
    "Label9": {},
    "LAST NAME_Column1_1": {},
    "LAST NAME_DataCardOCFP": {},
    "lastDate_card": {},
    "lastDate_card_1": {},
    "lastDate_input": {},
    "lastDate_input_1": {},
    "lastDate_label": {},
    "lastDate_label_1": {},
    "Lateral Transfer Form_1": {},
    "Lateral Transfer Form_2": {},
    "Lateral Transfer Form_3": {},
    "Lateral Transfer Form_4": {},
    "Lateral Transfer Form_5": {},
    "Lateral Transfer Form_6": {},
    "LateralTransfer_FirstPage": {},
    "LateralTransfer_SecondPage": {},
    "LineOfBusiness_Label_1": {},
    "lname_card": {},
    "lname_card_1": {},
    "lname_label": {},
    "lname_label_1": {},
    "lname_value": {},
    "lname_value_1": {},
    "lob_card": {},
    "lob_card_1": {},
    "LOB_Column1_1": {},
    "LOB_DataCard1": {},
    "LOB_DataCard2": {},
    "LOB_DataCard3": {},
    "LOB_DataCard4": {},
    "LOB_DataCard7": {},
    "LOB_DataCardOCFP": {},
    "lob_input": {},
    "lob_label": {},
    "lob_Label": {},
    "lob_label_1": {},
    "LOB_OTDataCard1": {},
    "lob_value": {},
    "lob_value_1": {},
    "MIDDLE NAME_Column1_1": {},
    "MIDDLE NAME_DataCardOCFP": {},
    "MultipleTerminationForm_Label": {},
    "MultipleTerminationForm_Label_1": {},
    "NESTING START DATE_DataCard1": {},
    "NESTING START DATE_DataCard3": {},
    "NewHireOnboarding_EditPage": {},
    "NewHireOnboarding_FirstPage": {},
    "NewHireOnboarding_SecondPage": {},
    "NextArrow2": {},
    "NextArrow2_1": {},
    "NextArrow2_1_Verify_1": {},
    "NextArrow3": {},
    "NextArrow3_1": {},
    "NextArrow4": {},
    "NextArrow4_2": {},
    "NextArrow4_2_Verify_1": {},
    "oc1": {},
    "oc2": {},
    "oc3": {},
    "omnia_input": {},
    "omniaID": {},
    "omniaID_1": {},
    "OT1": {},
    "OT2": {},
    "OT3": {},
    "OT4": {},
    "OT5": {},
    "OT6": {},
    "Others_FirstPage": {},
    "Others_SecondPage": {},
    "position_card": {},
    "position_card_1": {},
    "POSITION_Column1_1": {},
    "POSITION_DataCard PRMp1_1": {},
    "POSITION_DataCardOCFP": {},
    "position_label": {},
    "position_label_1": {},
    "POSITION_LTMDataCard": {},
    "POSITION_LTMDataCard2": {},
    "POSITION_OTDataCard": {},
    "POSITION_OTDataCard1": {},
    "POSITION_PRMDataCard2_2": {},
    "position_value": {},
    "position_value_1": {},
    "proceed_btn": {},
    "proceed_btn_1": {},
    "PRODUCTION DATE_DataCard1": {},
    "PRODUCTION DATE_DataCard3": {},
    "Promotion Form p2_1": {},
    "Promotion Form_1": {},
    "Promotion_FirstPage": {},
    "Promotion_SecondPage": {},
    "Promotion-Sub_LOB2": {},
    "Promotion-Sub_LOB2_Label": {},
    "rdLTMInternship": {},
    "rdPRInternship": {},
    "Rectangle1": {},
    "Rectangle2": {},
    "Rectangle3": {},
    "Rectangle3_1": {},
    "REGULARIZATION DATE_Column1": {},
    "Reminder": {},
    "Remove Button Container": {},
    "Remove_BTN": {},
    "Remove_Button": {},
    "REMOVE_BUTTON": {},
    "ROLE_Column1_1": {},
    "ROLE_DataCardOCFP": {},
    "Roster Update Selection": {},
    "Save Button Container": {},
    "Save_Button": {},
    "SAVE_BUTTON": {},
    "SAVE_BUTTON_LT": {},
    "SCHEDULE_OTDataCard": {},
    "SCHEDULE_OTDataCard1": {},
    "Separator2": {},
    "Separator2_1": {},
    "Separator2_1_Verify_1": {},
    "Separator3": {},
    "Separator3_1": {},
    "Separator4": {},
    "Separator4_2": {},
    "Separator4_2_Verify_1": {},
    "SITE DataCard PRMp1_1": {},
    "SITE_Column1_1": {},
    "Site_DataCard": {},
    "SITE_LTMDataCard": {},
    "SITE_LTMDataCard2": {},
    "SITE_OTDataCard": {},
    "SITE_OTDataCard1": {},
    "SITE_PRMDataCard_4": {},
    "START DATE_OTDataCard": {},
    "START DATE_OTDataCard1": {},
    "StarVisible1": {},
    "StarVisible2": {},
    "StarVisible3": {},
    "STATUS_Column1": {},
    "STATUS_DataCardOCFP": {},
    "STATUS_OTDataCard": {},
    "STATUS_OTDataCard1": {},
    "Sub-LOB": {},
    "SUB-LOB": {},
    "SUB-LOB_Column1_1": {},
    "Sub-LOB_DataCard": {},
    "SUB-LOB_DataCardOCFP": {},
    "SUB-LOB_OTDataCard": {},
    "SUB-LOB2_OTDataCard": {},
    "SUB-UNIT_Column1": {},
    "SUB-UNIT_DataCard PRMp1_1": {},
    "SUB-UNIT_DataCardOCFP": {},
    "SUB-UNIT_LTMDataCard": {},
    "SUB-UNIT_LTMDataCard2": {},
    "SUB-UNIT_OTDataCard": {},
    "SUB-UNIT_OTDataCard1": {},
    "SUB-UNIT_PRMDataCard2_2": {},
    "SUPERVISOR EMP ID": {},
    "SUPERVISOR EMP ID_Column1": {},
    "supervisor_card": {},
    "supervisor_card_1": {},
    "SUPERVISOR_Column1_1": {},
    "SUPERVISOR_DataCard PRMp1_1": {},
    "SUPERVISOR_EMAIL": {},
    "SUPERVISOR_EMAIL_LT": {},
    "supervisor_emp_id": {},
    "SUPERVISOR_EMP_ID": {},
    "SUPERVISOR_EMP_ID_PRMDataCard": {},
    "SUPERVISOR_LT": {},
    "SUPERVISOR_LTMDataCard": {},
    "SUPERVISOR_OTDataCard": {},
    "SUPERVISOR_OTDataCard1": {},
    "supervisor_value": {},
    "SupervisorEmail": {},
    "supervisorEmpID_1": {},
    "supervisorEmpID_value": {},
    "SUPERVISORS_EMAIL_LT": {},
    "tblOCSP": {},
    "TEAM_PRMDataCard2_2": {},
    "TEAMLEADEREMP.ID_DataCard1": {},
    "TEAMLEADEREMP.ID_DataCard2": {},
    "TEAMLEADEREMP.ID_DataCard3": {},
    "Termination Status Verify": {},
    "Termination_FirstPage": {},
    "Termination_VerificationPage": {},
    "terminationStatus_card": {},
    "terminationStatus_card_1": {},
    "terminationStatus_cb": {},
    "terminationStatus_label": {},
    "terminationStatus_label_1": {},
    "terminationType_card": {},
    "terminationType_card_1": {},
    "terminationType_cb": {},
    "terminationType_label": {},
    "terminationType_label_1": {},
    "Time_Zone": {},
    "TIME_ZONE": {},
    "trainer1": {},
    "Trainer1": {},
    "TRAINER1": {},
    "trainer2": {},
    "Trainer2": {},
    "TRAINER2": {},
    "trainer3": {},
    "Trainer3": {},
    "TRAINER3": {},
    "Treehouse Guide Group": {},
    "txtLTMultipleBillability2": {},
    "txtLTMultipleBusUnit2": {},
    "txtLTMultipleEmpId": {},
    "txtLTMultipleEmpId2": {},
    "txtLTMultipleName": {},
    "txtLTMultipleName_1": {},
    "txtLTMultipleName_2": {},
    "txtLTMultipleName_3": {},
    "txtLTMultipleOmnia": {},
    "txtLTMultipleOmnia_1": {},
    "txtLTMultipleOmnia_2": {},
    "txtLTMultiplePosition2": {},
    "txtLTMultipleSite": {},
    "txtLTMultipleSite2": {},
    "txtLTMultipleSubUnit2": {},
    "txtLTMutipleClient2": {},
    "txtLTSearchMultipleLOB": {},
    "txtLTSearchMultipleOmnia": {},
    "txtOCEPClassName": {},
    "txtOCEPEmpId": {},
    "txtOCEPFName": {},
    "txtOCEPInternalEmail": {},
    "txtOCEPLName": {},
    "txtOCEPMName": {},
    "txtOCEPSupervisorEmpID": {},
    "txtOCFPClassName": {},
    "txtOCFPEmpId": {},
    "txtOCFPFName": {},
    "txtOCFPLName": {},
    "txtOCFPMName": {},
    "txtOCFPSupervisorEmpId": {},
    "txtOCInternalEmail": {},
    "txtOTBillability1": {},
    "txtOTBusUnit1": {},
    "txtOTClient1": {},
    "txtOTEmpId": {},
    "txtOTEmpId1": {},
    "txtOTEndDate1": {},
    "txtOTLOB": {},
    "txtOTLOB1": {},
    "txtOTMName": {},
    "txtOTMOmnia": {},
    "txtOTNesting1": {},
    "txtOTOmnia": {},
    "txtOTPosition1": {},
    "txtOTProduction1": {},
    "txtOTSchedule": {},
    "txtOTSchedule1": {},
    "txtOTSite": {},
    "txtOTSite1": {},
    "txtOTStartdate1": {},
    "txtOTStatus1": {},
    "txtOTSubUnit1": {},
    "txtOTSupervisor1": {},
    "txtPREDp1_1": {},
    "txtPREDp2_1": {},
    "txtPRMultipleBILLpm2_1": {},
    "txtPRMultipleBUpm2_1": {},
    "txtPRMultipleCLpm2_1": {},
    "txtPRMultipleEmpName_1": {},
    "txtPRMultipleEmpNamepm2_1": {},
    "txtPRMultipleNamepm1_1": {},
    "txtPRMultipleOmniapm1": {},
    "txtPRMultipleOmniapm2_1": {},
    "txtPRMultiplePOSpm2_1": {},
    "txtPRMultipleSite_1": {},
    "txtPRMultipleSitepm2_1": {},
    "txtPRMultipleSUpm2_1": {},
    "txtPRMultipleSUPpm2_1": {},
    "txtPRSearchMultipleLOB_1": {},
    "txtPRSearchMultipleOmnia_1": {},
    "txtPRSEp1_1": {},
    "txtPRUEp2_1": {}
  },
  "PCFDynamicSchemaForIRRetrievalEntry": {},
  "PCFTemplateEntry": {},
  "PublishOrderIndices": {
    "address_card": 666,
    "address_card_1": 723,
    "address_input": 668,
    "address_input_1": 725,
    "address_label": 667,
    "address_label_1": 724,
    "ALVARIA ID_Column1": 121,
    "Alvaria_ID": 87,
    "App": 0,
    "BILLABILITY_Column1_1": 114,
    "BILLABILITY_DataCard PRMp1_1": 538,
    "BILLABILITY_DataCardOCFP": 68,
    "BILLABILITY_LTMDataCard": 247,
    "BILLABILITY_LTMDataCard2": 306,
    "BILLABILITY_OTDataCard": 368,
    "BILLABILITY_OTDataCard1": 451,
    "BILLABILITY_PRMDataCard2_2": 597,
    "btnFirstPageNext": 7,
    "btnLTMultipleBack": 266,
    "btnLTMultipleBack_1": 323,
    "btnLTMultipleBack_2": 493,
    "btnLTMultipleBack_3": 674,
    "btnLTMultipleBack_4": 731,
    "btnLTMultipleReview": 267,
    "btnLTMultipleReview_1": 324,
    "btnLTMultipleReview_2": 494,
    "btnLTRemove": 322,
    "btnLTRemove_1": 730,
    "btnOCEPBack": 202,
    "btnOCEPUpdate": 203,
    "btnOCFPBack": 96,
    "btnOCFPReview": 97,
    "btnOCFPSave": 95,
    "btnOCSPBack": 128,
    "btnOCSPEdit": 101,
    "btnOCSPRemove": 102,
    "btnOCSPSubmit": 129,
    "btnOTBack": 412,
    "btnOTRemove": 492,
    "btnOTReview": 413,
    "btnOTSave": 411,
    "btnPRMultipleBackp1_1": 557,
    "btnPRMultipleBackp2_1": 614,
    "btnPRMultipleReviewp1_1": 558,
    "btnPRMultipleSubmitp2_1": 615,
    "btnPRRemovep2_3": 613,
    "BUSINESS UNIT_Column1_1": 109,
    "BUSINESS UNIT_DataCard PRMp1_1": 517,
    "BUSINESS UNIT_DataCardOCFP": 40,
    "BUSINESS UNIT_LTMDataCard": 226,
    "BUSINESS UNIT_LTMDataCard2": 284,
    "BUSINESS UNIT_OTDataCard": 350,
    "BUSINESS UNIT_OTDataCard1": 433,
    "BUSINESS UNIT_PRMDataCard_4": 575,
    "Button1": 94,
    "Button2": 673,
    "Button5": 556,
    "Button6": 265,
    "campaign_card": 645,
    "campaign_card_1": 702,
    "CAMPAIGN_Column1_1": 112,
    "campaign_label": 646,
    "campaign_label_1": 703,
    "campaign_value": 647,
    "campaign_value_1": 704,
    "cbLTMultipleBillability": 248,
    "cbLTMultipleBusUnit": 227,
    "cbLTMultipleClient": 239,
    "cbLTMultipleLOB": 242,
    "cbLTMultiplePosition": 233,
    "cbLTMultipleSubLOB": 245,
    "cbLTMultipleSubUnit": 230,
    "cbLTMultipleSupervisor": 251,
    "cbLTMultipleSupervisorEmail_1": 254,
    "cbLTMultipleSupervisorEmpID_1": 257,
    "cbLTSearchMultipleLOB": 208,
    "cbLTSearchMultipleOmnia": 209,
    "cbOCEPAlvariaID": 183,
    "cbOCEPBillability": 186,
    "cbOCEPBusUnit": 160,
    "cbOCEPCampaign": 161,
    "cbOCEPClient": 200,
    "cbOCEPCountry": 158,
    "cbOCEPEmpStatus": 192,
    "cbOCEPLOB": 169,
    "cbOCEPPosition": 177,
    "cbOCEPRole": 175,
    "cbOCEPSite": 167,
    "cbOCEPStatus": 185,
    "cbOCEPSubLOB": 178,
    "cbOCEPSubUnit": 170,
    "cbOCEPSupervisor": 193,
    "cbOCFPAlvariaID": 89,
    "cbOCFPBillability": 70,
    "cbOCFPBusUnit": 42,
    "cbOCFPClient": 57,
    "cbOCFPCountry": 83,
    "cbOCFPDivision": 61,
    "cbOCFPEmpStatus": 54,
    "cbOCFPLOB": 64,
    "cbOCFPPosition": 48,
    "cbOCFPRole": 86,
    "cbOCFPSite": 80,
    "cbOCFPStatus": 51,
    "cbOCFPSubLOB": 67,
    "cbOCFPSubUnit": 45,
    "cbOCFPSupervisor": 73,
    "cbOTBillability": 369,
    "cbOTBusUnit": 351,
    "cbOTClient": 363,
    "cbOTLOB": 404,
    "cbOTOmnia": 328,
    "cbOTPosition": 398,
    "cbOTSearchLOB": 330,
    "cbOTStatus": 354,
    "cbOTSub-LOB": 345,
    "cbOTSubUnit": 357,
    "cbOTSupervisor": 384,
    "cbOTSupervisorEmpID": 390,
    "cbPRMultipleBillability_1": 539,
    "cbPRMultipleBusUnit_1": 518,
    "cbPRMultipleClient_1": 530,
    "cbPRMultipleLOB_2": 533,
    "cbPRMultiplePosition_1": 524,
    "cbPRMultipleSub-LOB": 536,
    "cbPRMultipleSubUnit_1": 521,
    "cbPRMultipleSupervisor_1": 542,
    "cbPRMultipleSupervisorEmail_1": 550,
    "cbPRMultipleSupervisorEmpID_1": 545,
    "cbPRSearchMultipleLOB": 498,
    "cbPRSearchMultipleOmnia": 500,
    "CLASS NAME_Column1": 122,
    "class_name": 408,
    "Class_Name": 488,
    "CLASS_NAME": 409,
    "ClassName": 407,
    "CLIENT_Column1_1": 111,
    "CLIENT_DataCard PRMp1_1": 529,
    "CLIENT_LTMDataCard": 238,
    "CLIENT_LTMDataCard2": 296,
    "CLIENT_OTDataCard": 362,
    "CLIENT_OTDataCard1": 445,
    "CLIENT_PRMDataCard2_2": 587,
    "comment_card": 669,
    "comment_card_1": 726,
    "comment_input": 671,
    "comment_input_1": 728,
    "comment_label": 670,
    "comment_label_1": 727,
    "COUNTRY_Column1_1": 115,
    "Country_DataCard": 74,
    "Country_DataCard1": 81,
    "CS FreshService": 12,
    "CS FreshService Group": 9,
    "DataCard10": 90,
    "DataCard2": 55,
    "DataCard3": 71,
    "DataCard7": 293,
    "DataCard8": 59,
    "DataCardKey1": 279,
    "DataCardKey1_1": 425,
    "DataCardKey10": 31,
    "DataCardKey11": 37,
    "DataCardKey12": 259,
    "DataCardKey13": 373,
    "DataCardKey14": 379,
    "DataCardKey15": 392,
    "DataCardKey15_1": 44,
    "DataCardKey16": 547,
    "DataCardKey16_1": 47,
    "DataCardKey18": 455,
    "DataCardKey19": 461,
    "DataCardKey2": 243,
    "DataCardKey24": 221,
    "DataCardKey24_1": 342,
    "DataCardKey27": 437,
    "DataCardKey28": 443,
    "DataCardKey29": 449,
    "DataCardKey3": 534,
    "DataCardKey35": 66,
    "DataCardKey36": 288,
    "DataCardKey36_1": 440,
    "DataCardKey37": 228,
    "DataCardKey37_1": 285,
    "DataCardKey37_2": 352,
    "DataCardKey37_3": 434,
    "DataCardKey38": 231,
    "DataCardKey38_1": 358,
    "DataCardKey39": 240,
    "DataCardKey39_1": 364,
    "DataCardKey4": 300,
    "DataCardKey40": 249,
    "DataCardKey40_1": 370,
    "DataCardKey41": 234,
    "DataCardKey41_1": 399,
    "DataCardKey42": 252,
    "DataCardKey42_1": 385,
    "DataCardKey43_1": 376,
    "DataCardKey44": 291,
    "DataCardKey44_1": 479,
    "DataCardKey45": 297,
    "DataCardKey45_1": 446,
    "DataCardKey46": 63,
    "DataCardKey47": 224,
    "DataCardKey47_1": 282,
    "DataCardKey47_2": 348,
    "DataCardKey47_3": 431,
    "DataCardKey48": 69,
    "DataCardKey5": 405,
    "DataCardKey50": 307,
    "DataCardKey50_1": 452,
    "DataCardKey51_1": 458,
    "DataCardKey52_1": 467,
    "DataCardKey55": 85,
    "DataCardKey56": 22,
    "DataCardKey6": 25,
    "DataCardKey7": 485,
    "DataCardKey8": 591,
    "DataCardKey9": 28,
    "DataCardKeyBILLpm1_1": 540,
    "DataCardKeyBILLPRpm2_1": 598,
    "DataCardKeyBUpm1_1": 519,
    "DataCardKeyBUPRpm2_1": 576,
    "DataCardKeyCLpm1_1": 531,
    "DataCardKeyCLPRpm2_1": 588,
    "DataCardKeyENpm1_1": 512,
    "DataCardKeyENPRpm2_1": 570,
    "DataCardKeyPOSpm1_1": 525,
    "DataCardKeyPOSPRpm2_1": 582,
    "DataCardKeySITEpm1_1": 515,
    "DataCardKeySITEPRpm2_1": 573,
    "DataCardKeySUpm1_1": 522,
    "DataCardKeySUPpm1_1": 543,
    "DataCardKeySUPPRpm2_1": 601,
    "DataCardKeySUPRpm2_1": 579,
    "DataCardValue2": 302,
    "DataCardValue4": 593,
    "dateEnd": 366,
    "dateNesting": 372,
    "dateOCEPHireDate": 191,
    "dateOCFPHireDate": 38,
    "dateProduction": 378,
    "dateStart": 360,
    "dpLTEffectivityDate": 262,
    "dpPREffectivityDate": 553,
    "drpOTtimezone": 381,
    "drpRosterSelection": 5,
    "EFFECTIVITY_DATE": 552,
    "EFFECTIVITY_DATE_LT": 261,
    "EffectivityDate": 609,
    "effectivityDate_card": 660,
    "effectivityDate_card_1": 717,
    "effectivityDate_input": 662,
    "effectivityDate_input_1": 719,
    "effectivityDate_label": 661,
    "effectivityDate_label_1": 718,
    "EFFECTIVITYDATE_LT": 318,
    "email_card": 642,
    "email_card_1": 699,
    "email_label": 643,
    "email_label_1": 700,
    "email_value": 644,
    "email_value_1": 701,
    "EMPLOYEE ID_Column1_1": 104,
    "EMPLOYEE ID_DataCard1": 278,
    "EMPLOYEE ID_DataCardOCFP": 21,
    "EMPLOYEE ID_LTMDataCard": 220,
    "EMPLOYEE ID_OTDataCard": 341,
    "EMPLOYEE ID_OTDataCard1": 424,
    "EMPLOYEE NAME_PRMDataCard_3": 569,
    "EmployeeGallery": 623,
    "EmployeeGallery_1": 679,
    "employeeID_1": 684,
    "EmployeeInfo_form": 629,
    "EmployeeInfo_form_1": 686,
    "employeeInfo_label": 622,
    "employeeInfo_label_1": 678,
    "employeeList_label": 621,
    "employeeList_label_1": 677,
    "employeeName": 625,
    "employeeName_1": 681,
    "EMPLOYEESTATUS_DataCard12": 52,
    "EMPLOYMENT STATUS_Column1": 119,
    "END DATE_OTDataCard": 365,
    "END DATE_OTDataCard1": 448,
    "ErrorMessage1": 260,
    "ErrorMessage2": 393,
    "ErrorMessage3": 548,
    "FIRST NAME_Column1_1": 105,
    "FIRST NAME_DataCardOCFP": 24,
    "fname_card": 630,
    "fname_card_1": 687,
    "fname_label": 631,
    "fname_label_1": 688,
    "fname_value": 632,
    "fname_value_1": 689,
    "formLTM": 219,
    "formLTM2": 277,
    "formOCFirstPage1": 20,
    "formOCFirstPage2": 39,
    "formOCFirstPage3": 58,
    "formOCFirstPage4": 77,
    "formOT": 340,
    "formOT1": 423,
    "formPREDsp2": 510,
    "formPREDsp2_1": 568,
    "FULL NAME_DataCard PRMp1_1": 511,
    "galleryLTM": 213,
    "galleryLTM_1": 271,
    "galleryLTM_2": 417,
    "galleryOT": 334,
    "galleryPRMp1st_1": 504,
    "galleryPRMp2nd_1": 562,
    "galleryTemplate2": 214,
    "galleryTemplate2_1": 272,
    "galleryTemplate2_2": 335,
    "galleryTemplate2_3": 418,
    "galleryTemplate2_4": 505,
    "galleryTemplate2_5": 563,
    "galleryTemplate3": 624,
    "galleryTemplate3_1": 680,
    "galleryTemplate6": 135,
    "galOCEP": 132,
    "grpLTSearchMultipleLOB": 205,
    "grpLTSearchMultipleOmnia": 206,
    "grpNewOCForm": 17,
    "grpOCECountry": 141,
    "grpOCEPBillability": 133,
    "grpOCEPBusUnit": 152,
    "grpOCEPButtons": 130,
    "grpOCEPCampaign": 145,
    "grpOCEPClient": 144,
    "grpOCEPEmpId": 162,
    "grpOCEPEmpStatus": 156,
    "grpOCEPFName": 148,
    "grpOCEPHireDate": 151,
    "grpOCEPInternalEmail": 157,
    "grpOCEPLName": 150,
    "grpOCEPLOB": 146,
    "grpOCEPMName": 149,
    "grpOCEPPosition": 154,
    "grpOCEPRole": 143,
    "grpOCEPRole_1": 134,
    "grpOCEPSite": 142,
    "grpOCEPStatus": 155,
    "grpOCEPSubLOB": 147,
    "grpOCEPSubUnit": 153,
    "grpOCEPSupervisor": 140,
    "grpOCFPButtons": 18,
    "grpOCSPActions": 100,
    "grpOCSPButtons": 99,
    "grpOTLOB": 326,
    "grpOTOmnia": 327,
    "grpPRSearchMultipleLOB_1": 497,
    "grpPRSearchMultipleOmnia_1": 499,
    "HIRE DATE_Column1_1": 108,
    "HIRE DATE_DataCardOCFP": 36,
    "HomePage": 2,
    "Host": 0,
    "Image2": 13,
    "INTERNAL EMAIL": 33,
    "INTERNAL EMAIL_Column1": 120,
    "INTERNSHIP_DataCard": 526,
    "INTERNSHIP_LTMDataCard": 235,
    "INTERNSHIP_PRMDataCard_2": 584,
    "Label1": 713,
    "Label10": 402,
    "Label11": 585,
    "Label12": 586,
    "Label13": 236,
    "Label14": 490,
    "Label15": 295,
    "Label16": 294,
    "Label17": 470,
    "Label18": 382,
    "Label19": 2,
    "Label19_1": 6,
    "Label2": 355,
    "Label20": 464,
    "Label21": 465,
    "Label22": 60,
    "Label23": 3,
    "Label24": 79,
    "Label25": 41,
    "Label26": 476,
    "Label27": 50,
    "Label28": 482,
    "Label29": 53,
    "Label3": 361,
    "Label30": 471,
    "Label31": 483,
    "Label32": 489,
    "Label33": 477,
    "Label34": 319,
    "Label35": 320,
    "Label36": 310,
    "Label37": 34,
    "Label38": 311,
    "Label39": 554,
    "Label4": 367,
    "Label40": 610,
    "Label41": 611,
    "Label42": 14,
    "Label42_1": 15,
    "Label43": 195,
    "Label44": 551,
    "Label45": 255,
    "Label46": 604,
    "Label47": 605,
    "Label48": 313,
    "Label49": 314,
    "Label5": 137,
    "Label5_1": 163,
    "Label5_10": 196,
    "Label5_11": 139,
    "Label5_12": 166,
    "Label5_13": 173,
    "Label5_14": 190,
    "Label5_15": 136,
    "Label5_16": 164,
    "Label5_17": 171,
    "Label5_18": 182,
    "Label5_19": 179,
    "Label5_2": 172,
    "Label5_20": 197,
    "Label5_21": 187,
    "Label5_3": 180,
    "Label5_4": 188,
    "Label5_5": 138,
    "Label5_6": 165,
    "Label5_7": 174,
    "Label5_8": 189,
    "Label5_9": 181,
    "Label50": 56,
    "Label51": 72,
    "Label52": 75,
    "Label53": 88,
    "Label54": 93,
    "Label54_1": 198,
    "Label55": 246,
    "Label56": 304,
    "Label57": 305,
    "Label58": 537,
    "Label59": 82,
    "Label6": 263,
    "Label60": 596,
    "Label61": 346,
    "Label62": 428,
    "Label63": 429,
    "Label64": 91,
    "Label65": 316,
    "Label66": 317,
    "Label67": 473,
    "Label68": 474,
    "Label69": 607,
    "Label7": 527,
    "Label70": 608,
    "Label71": 649,
    "Label72": 406,
    "Label73": 652,
    "Label74": 486,
    "Label75": 706,
    "Label76": 707,
    "Label77": 709,
    "Label78": 710,
    "Label79": 592,
    "Label8": 388,
    "Label80": 301,
    "Label9": 396,
    "LAST NAME_Column1_1": 107,
    "LAST NAME_DataCardOCFP": 30,
    "lastDate_card": 663,
    "lastDate_card_1": 720,
    "lastDate_input": 665,
    "lastDate_input_1": 722,
    "lastDate_label": 664,
    "lastDate_label_1": 721,
    "Lateral Transfer Form_1": 204,
    "Lateral Transfer Form_2": 211,
    "Lateral Transfer Form_3": 212,
    "Lateral Transfer Form_4": 268,
    "Lateral Transfer Form_5": 269,
    "Lateral Transfer Form_6": 270,
    "LateralTransfer_FirstPage": 0,
    "LateralTransfer_SecondPage": 0,
    "LineOfBusiness_Label_1": 619,
    "lname_card": 633,
    "lname_card_1": 690,
    "lname_label": 634,
    "lname_label_1": 692,
    "lname_value": 635,
    "lname_value_1": 691,
    "lob_card": 639,
    "lob_card_1": 696,
    "LOB_Column1_1": 113,
    "LOB_DataCard1": 241,
    "LOB_DataCard2": 532,
    "LOB_DataCard3": 299,
    "LOB_DataCard4": 403,
    "LOB_DataCard7": 590,
    "LOB_DataCardOCFP": 62,
    "lob_input": 618,
    "lob_label": 640,
    "lob_Label": 617,
    "lob_label_1": 698,
    "LOB_OTDataCard1": 484,
    "lob_value": 641,
    "lob_value_1": 697,
    "MIDDLE NAME_Column1_1": 106,
    "MIDDLE NAME_DataCardOCFP": 27,
    "MultipleTerminationForm_Label": 616,
    "MultipleTerminationForm_Label_1": 676,
    "NESTING START DATE_DataCard1": 371,
    "NESTING START DATE_DataCard3": 454,
    "NewHireOnboarding_EditPage": 0,
    "NewHireOnboarding_FirstPage": 0,
    "NewHireOnboarding_SecondPage": 0,
    "NextArrow2": 216,
    "NextArrow2_1": 337,
    "NextArrow2_1_Verify_1": 507,
    "NextArrow3": 274,
    "NextArrow3_1": 420,
    "NextArrow4": 626,
    "NextArrow4_2": 682,
    "NextArrow4_2_Verify_1": 565,
    "oc1": 16,
    "oc2": 98,
    "oc3": 131,
    "omnia_input": 620,
    "omniaID": 627,
    "omniaID_1": 683,
    "OT1": 325,
    "OT2": 333,
    "OT3": 332,
    "OT4": 416,
    "OT5": 415,
    "OT6": 414,
    "Others_FirstPage": 0,
    "Others_SecondPage": 0,
    "position_card": 636,
    "position_card_1": 693,
    "POSITION_Column1_1": 110,
    "POSITION_DataCard PRMp1_1": 523,
    "POSITION_DataCardOCFP": 46,
    "position_label": 637,
    "position_label_1": 694,
    "POSITION_LTMDataCard": 232,
    "POSITION_LTMDataCard2": 290,
    "POSITION_OTDataCard": 397,
    "POSITION_OTDataCard1": 478,
    "POSITION_PRMDataCard2_2": 581,
    "position_value": 638,
    "position_value_1": 695,
    "proceed_btn": 675,
    "proceed_btn_1": 732,
    "PRODUCTION DATE_DataCard1": 377,
    "PRODUCTION DATE_DataCard3": 460,
    "Promotion Form p2_1": 559,
    "Promotion Form_1": 495,
    "Promotion_FirstPage": 314,
    "Promotion_SecondPage": 362,
    "Promotion-Sub_LOB2": 594,
    "Promotion-Sub_LOB2_Label": 595,
    "rdLTMInternship": 237,
    "rdPRInternship": 528,
    "Rectangle1": 19,
    "Rectangle2": 0,
    "Rectangle3": 8,
    "Rectangle3_1": 10,
    "REGULARIZATION DATE_Column1": 117,
    "Reminder": 1,
    "Remove Button Container": 729,
    "Remove_BTN": 321,
    "Remove_Button": 612,
    "REMOVE_BUTTON": 491,
    "ROLE_Column1_1": 116,
    "ROLE_DataCardOCFP": 84,
    "Roster Update Selection": 4,
    "Save Button Container": 672,
    "Save_Button": 410,
    "SAVE_BUTTON": 555,
    "SAVE_BUTTON_LT": 264,
    "SCHEDULE_OTDataCard": 374,
    "SCHEDULE_OTDataCard1": 457,
    "Separator2": 218,
    "Separator2_1": 339,
    "Separator2_1_Verify_1": 509,
    "Separator3": 276,
    "Separator3_1": 422,
    "Separator4": 628,
    "Separator4_2": 685,
    "Separator4_2_Verify_1": 567,
    "SITE DataCard PRMp1_1": 514,
    "SITE_Column1_1": 127,
    "Site_DataCard": 78,
    "SITE_LTMDataCard": 223,
    "SITE_LTMDataCard2": 281,
    "SITE_OTDataCard": 347,
    "SITE_OTDataCard1": 430,
    "SITE_PRMDataCard_4": 572,
    "START DATE_OTDataCard": 359,
    "START DATE_OTDataCard1": 442,
    "StarVisible1": 258,
    "StarVisible2": 391,
    "StarVisible3": 546,
    "STATUS_Column1": 118,
    "STATUS_DataCardOCFP": 49,
    "STATUS_OTDataCard": 353,
    "STATUS_OTDataCard1": 436,
    "Sub-LOB": 535,
    "SUB-LOB": 303,
    "SUB-LOB_Column1_1": 125,
    "Sub-LOB_DataCard": 244,
    "SUB-LOB_DataCardOCFP": 65,
    "SUB-LOB_OTDataCard": 344,
    "SUB-LOB2_OTDataCard": 427,
    "SUB-UNIT_Column1": 124,
    "SUB-UNIT_DataCard PRMp1_1": 520,
    "SUB-UNIT_DataCardOCFP": 43,
    "SUB-UNIT_LTMDataCard": 229,
    "SUB-UNIT_LTMDataCard2": 287,
    "SUB-UNIT_OTDataCard": 356,
    "SUB-UNIT_OTDataCard1": 439,
    "SUB-UNIT_PRMDataCard2_2": 578,
    "SUPERVISOR EMP ID": 315,
    "SUPERVISOR EMP ID_Column1": 123,
    "supervisor_card": 648,
    "supervisor_card_1": 705,
    "SUPERVISOR_Column1_1": 126,
    "SUPERVISOR_DataCard PRMp1_1": 541,
    "SUPERVISOR_EMAIL": 549,
    "SUPERVISOR_EMAIL_LT": 253,
    "supervisor_emp_id": 651,
    "SUPERVISOR_EMP_ID": 472,
    "SUPERVISOR_EMP_ID_PRMDataCard": 606,
    "SUPERVISOR_LT": 309,
    "SUPERVISOR_LTMDataCard": 250,
    "SUPERVISOR_OTDataCard": 383,
    "SUPERVISOR_OTDataCard1": 466,
    "supervisor_value": 650,
    "SupervisorEmail": 603,
    "supervisorEmpID_1": 708,
    "supervisorEmpID_value": 653,
    "SUPERVISORS_EMAIL_LT": 312,
    "tblOCSP": 103,
    "TEAM_PRMDataCard2_2": 600,
    "TEAMLEADEREMP.ID_DataCard1": 256,
    "TEAMLEADEREMP.ID_DataCard2": 389,
    "TEAMLEADEREMP.ID_DataCard3": 544,
    "Termination Status Verify": 716,
    "Termination_FirstPage": 208,
    "Termination_VerificationPage": 264,
    "terminationStatus_card": 657,
    "terminationStatus_card_1": 714,
    "terminationStatus_cb": 659,
    "terminationStatus_label": 658,
    "terminationStatus_label_1": 715,
    "terminationType_card": 654,
    "terminationType_card_1": 711,
    "terminationType_cb": 656,
    "terminationType_label": 655,
    "terminationType_label_1": 712,
    "Time_Zone": 380,
    "TIME_ZONE": 463,
    "trainer1": 387,
    "Trainer1": 469,
    "TRAINER1": 386,
    "trainer2": 395,
    "Trainer2": 475,
    "TRAINER2": 394,
    "trainer3": 401,
    "Trainer3": 481,
    "TRAINER3": 400,
    "Treehouse Guide Group": 11,
    "txtLTMultipleBillability2": 308,
    "txtLTMultipleBusUnit2": 286,
    "txtLTMultipleEmpId": 222,
    "txtLTMultipleEmpId2": 280,
    "txtLTMultipleName": 215,
    "txtLTMultipleName_1": 273,
    "txtLTMultipleName_2": 419,
    "txtLTMultipleName_3": 564,
    "txtLTMultipleOmnia": 217,
    "txtLTMultipleOmnia_1": 275,
    "txtLTMultipleOmnia_2": 421,
    "txtLTMultiplePosition2": 292,
    "txtLTMultipleSite": 225,
    "txtLTMultipleSite2": 283,
    "txtLTMultipleSubUnit2": 289,
    "txtLTMutipleClient2": 298,
    "txtLTSearchMultipleLOB": 207,
    "txtLTSearchMultipleOmnia": 210,
    "txtOCEPClassName": 194,
    "txtOCEPEmpId": 159,
    "txtOCEPFName": 168,
    "txtOCEPInternalEmail": 199,
    "txtOCEPLName": 184,
    "txtOCEPMName": 176,
    "txtOCEPSupervisorEmpID": 201,
    "txtOCFPClassName": 92,
    "txtOCFPEmpId": 23,
    "txtOCFPFName": 26,
    "txtOCFPLName": 32,
    "txtOCFPMName": 29,
    "txtOCFPSupervisorEmpId": 76,
    "txtOCInternalEmail": 35,
    "txtOTBillability1": 453,
    "txtOTBusUnit1": 435,
    "txtOTClient1": 447,
    "txtOTEmpId": 343,
    "txtOTEmpId1": 426,
    "txtOTEndDate1": 450,
    "txtOTLOB": 329,
    "txtOTLOB1": 487,
    "txtOTMName": 336,
    "txtOTMOmnia": 338,
    "txtOTNesting1": 456,
    "txtOTOmnia": 331,
    "txtOTPosition1": 480,
    "txtOTProduction1": 462,
    "txtOTSchedule": 375,
    "txtOTSchedule1": 459,
    "txtOTSite": 349,
    "txtOTSite1": 432,
    "txtOTStartdate1": 444,
    "txtOTStatus1": 438,
    "txtOTSubUnit1": 441,
    "txtOTSupervisor1": 468,
    "txtPREDp1_1": 503,
    "txtPREDp2_1": 561,
    "txtPRMultipleBILLpm2_1": 599,
    "txtPRMultipleBUpm2_1": 577,
    "txtPRMultipleCLpm2_1": 589,
    "txtPRMultipleEmpName_1": 513,
    "txtPRMultipleEmpNamepm2_1": 571,
    "txtPRMultipleNamepm1_1": 506,
    "txtPRMultipleOmniapm1": 508,
    "txtPRMultipleOmniapm2_1": 566,
    "txtPRMultiplePOSpm2_1": 583,
    "txtPRMultipleSite_1": 516,
    "txtPRMultipleSitepm2_1": 574,
    "txtPRMultipleSUpm2_1": 580,
    "txtPRMultipleSUPpm2_1": 602,
    "txtPRSearchMultipleLOB_1": 496,
    "txtPRSearchMultipleOmnia_1": 501,
    "txtPRSEp1_1": 502,
    "txtPRUEp2_1": 560
  },
  "ResourcesJsonIndices": {
    "Image-bit.ly_CSFreshService": 6,
    "Image-bit.ly_DynamicRosterUpdateApplication-Treehouse": 7,
    "Image-homeScreen": 4,
    "Image-homeScreen2": 5,
    "Image-MicrosoftTeams-image": 2,
    "Image-MicrosoftTeams-image (2)": 1,
    "Image-SampleImage": 0,
    "Image-Untitled design 29": 3
  },
  "RuleScreenIdWithoutScreen": {},
  "TemplateVersions": {},
  "VolatileProperties": {
    "AnalysisLoadTime": 3.8376397,
    "ControlCount": {
      "button": 35,
      "combobox": 66,
      "dataTable": 1,
      "dataTableColumn": 24,
      "datepicker": 12,
      "dropdown": 4,
      "form": 12,
      "gallery": 9,
      "galleryTemplate": 9,
      "group": 35,
      "htmlViewer": 12,
      "icon": 8,
      "image": 2,
      "label": 306,
      "radio": 2,
      "rectangle": 12,
      "screen": 12,
      "text": 25,
      "typedDataCard": 159
    },
    "DeserializationLoadTime": 6.237045
  },
  "WasLocalDatabaseReferencesEmpty": true
}