{
  "ComponentIndexes": {},
  "ControlUniqueGuids": {},
  "ControlUniqueIds": {
    "address_card": 465,
    "address_card_1": 215,
    "address_input": 467,
    "address_input_1": 217,
    "address_label": 466,
    "address_label_1": 216,
    "ALVARIA ID_Column1": 740,
    "Alvaria_ID": 699,
    "App": 1,
    "BILLABILITY_Column1_1": 734,
    "BILLABILITY_DataCard PRMp1_1": 46,
    "BILLABILITY_DataCardOCFP": 680,
    "BILLABILITY_LTMDataCard": 606,
    "BILLABILITY_LTMDataCard2": 263,
    "BILLABILITY_OTDataCard": 517,
    "BILLABILITY_OTDataCard1": 124,
    "BILLABILITY_PRMDataCard2_2": 320,
    "btnFirstPageNext": 76,
    "btnLTMultipleBack": 625,
    "btnLTMultipleBack_1": 280,
    "btnLTMultipleBack_2": 165,
    "btnLTMultipleBack_3": 473,
    "btnLTMultipleBack_4": 223,
    "btnLTMultipleReview": 626,
    "btnLTMultipleReview_1": 281,
    "btnLTMultipleReview_2": 166,
    "btnLTRemove": 279,
    "btnLTRemove_1": 222,
    "btnOCEPBack": 411,
    "btnOCEPUpdate": 412,
    "btnOCFPBack": 708,
    "btnOCFPReview": 709,
    "btnOCFPSave": 707,
    "btnOCSPBack": 741,
    "btnOCSPEdit": 714,
    "btnOCSPRemove": 715,
    "btnOCSPSubmit": 742,
    "btnOTBack": 560,
    "btnOTRemove": 164,
    "btnOTReview": 561,
    "btnOTSave": 559,
    "btnPRMultipleBackp1_1": 65,
    "btnPRMultipleBackp2_1": 337,
    "btnPRMultipleReviewp1_1": 66,
    "btnPRMultipleSubmitp2_1": 338,
    "btnPRRemovep2_3": 336,
    "BUSINESS UNIT_Column1_1": 726,
    "BUSINESS UNIT_DataCard PRMp1_1": 25,
    "BUSINESS UNIT_DataCardOCFP": 652,
    "BUSINESS UNIT_LTMDataCard": 585,
    "BUSINESS UNIT_LTMDataCard2": 242,
    "BUSINESS UNIT_OTDataCard": 499,
    "BUSINESS UNIT_OTDataCard1": 106,
    "BUSINESS UNIT_PRMDataCard_4": 299,
    "Button1": 706,
    "Button2": 472,
    "Button5": 64,
    "Button6": 624,
    "campaign_card": 444,
    "campaign_card_1": 194,
    "CAMPAIGN_Column1_1": 730,
    "campaign_label": 445,
    "campaign_label_1": 195,
    "campaign_value": 446,
    "campaign_value_1": 196,
    "cbLTMultipleBillability": 607,
    "cbLTMultipleBusUnit": 586,
    "cbLTMultipleClient": 598,
    "cbLTMultipleLOB": 601,
    "cbLTMultiplePosition": 592,
    "cbLTMultipleSubLOB": 604,
    "cbLTMultipleSubUnit": 589,
    "cbLTMultipleSupervisor": 610,
    "cbLTMultipleSupervisorEmail_1": 613,
    "cbLTMultipleSupervisorEmpID_1": 616,
    "cbLTSearchMultipleLOB": 567,
    "cbLTSearchMultipleOmnia": 568,
    "cbOCEPAlvariaID": 371,
    "cbOCEPBillability": 374,
    "cbOCEPBusUnit": 349,
    "cbOCEPCampaign": 350,
    "cbOCEPClient": 388,
    "cbOCEPCountry": 347,
    "cbOCEPEmpStatus": 380,
    "cbOCEPLOB": 357,
    "cbOCEPPosition": 365,
    "cbOCEPRole": 363,
    "cbOCEPSite": 355,
    "cbOCEPStatus": 373,
    "cbOCEPSubLOB": 366,
    "cbOCEPSubUnit": 358,
    "cbOCEPSupervisor": 381,
    "cbOCFPAlvariaID": 701,
    "cbOCFPBillability": 682,
    "cbOCFPBusUnit": 654,
    "cbOCFPClient": 669,
    "cbOCFPCountry": 695,
    "cbOCFPDivision": 673,
    "cbOCFPEmpStatus": 666,
    "cbOCFPLOB": 676,
    "cbOCFPPosition": 660,
    "cbOCFPRole": 698,
    "cbOCFPSite": 692,
    "cbOCFPStatus": 663,
    "cbOCFPSubLOB": 679,
    "cbOCFPSubUnit": 657,
    "cbOCFPSupervisor": 685,
    "cbOTBillability": 518,
    "cbOTBusUnit": 500,
    "cbOTClient": 512,
    "cbOTLOB": 553,
    "cbOTOmnia": 477,
    "cbOTPosition": 547,
    "cbOTSearchLOB": 479,
    "cbOTStatus": 503,
    "cbOTSub-LOB": 494,
    "cbOTSubUnit": 506,
    "cbOTSupervisor": 533,
    "cbOTSupervisorEmpID": 539,
    "cbPRMultipleBillability_1": 47,
    "cbPRMultipleBusUnit_1": 26,
    "cbPRMultipleClient_1": 38,
    "cbPRMultipleLOB_2": 41,
    "cbPRMultiplePosition_1": 32,
    "cbPRMultipleSub-LOB": 44,
    "cbPRMultipleSubUnit_1": 29,
    "cbPRMultipleSupervisor_1": 50,
    "cbPRMultipleSupervisorEmail_1": 58,
    "cbPRMultipleSupervisorEmpID_1": 53,
    "cbPRSearchMultipleLOB": 7,
    "cbPRSearchMultipleOmnia": 8,
    "CLASS NAME_Column1": 731,
    "class_name": 556,
    "Class_Name": 160,
    "CLASS_NAME": 557,
    "ClassName": 555,
    "CLIENT_Column1_1": 729,
    "CLIENT_DataCard PRMp1_1": 37,
    "CLIENT_LTMDataCard": 597,
    "CLIENT_LTMDataCard2": 254,
    "CLIENT_OTDataCard": 511,
    "CLIENT_OTDataCard1": 118,
    "CLIENT_PRMDataCard2_2": 311,
    "comment_card": 468,
    "comment_card_1": 218,
    "comment_input": 470,
    "comment_input_1": 220,
    "comment_label": 469,
    "comment_label_1": 219,
    "COUNTRY_Column1_1": 737,
    "Country_DataCard": 686,
    "Country_DataCard1": 693,
    "CS FreshService": 79,
    "CS FreshService Group": 84,
    "DataCard10": 702,
    "DataCard2": 667,
    "DataCard3": 683,
    "DataCard7": 251,
    "DataCard8": 671,
    "DataCardKey1": 237,
    "DataCardKey1_1": 98,
    "DataCardKey10": 643,
    "DataCardKey11": 649,
    "DataCardKey12": 618,
    "DataCardKey13": 522,
    "DataCardKey14": 528,
    "DataCardKey15": 541,
    "DataCardKey15_1": 656,
    "DataCardKey16": 55,
    "DataCardKey16_1": 659,
    "DataCardKey18": 128,
    "DataCardKey19": 134,
    "DataCardKey2": 602,
    "DataCardKey24": 580,
    "DataCardKey24_1": 491,
    "DataCardKey27": 110,
    "DataCardKey28": 116,
    "DataCardKey29": 122,
    "DataCardKey3": 42,
    "DataCardKey35": 678,
    "DataCardKey36": 246,
    "DataCardKey36_1": 113,
    "DataCardKey37": 587,
    "DataCardKey37_1": 243,
    "DataCardKey37_2": 501,
    "DataCardKey37_3": 107,
    "DataCardKey38": 590,
    "DataCardKey38_1": 507,
    "DataCardKey39": 599,
    "DataCardKey39_1": 513,
    "DataCardKey4": 258,
    "DataCardKey40": 608,
    "DataCardKey40_1": 519,
    "DataCardKey41": 593,
    "DataCardKey41_1": 548,
    "DataCardKey42": 611,
    "DataCardKey42_1": 534,
    "DataCardKey43_1": 525,
    "DataCardKey44": 249,
    "DataCardKey44_1": 152,
    "DataCardKey45": 255,
    "DataCardKey45_1": 119,
    "DataCardKey46": 675,
    "DataCardKey47": 583,
    "DataCardKey47_1": 240,
    "DataCardKey47_2": 497,
    "DataCardKey47_3": 104,
    "DataCardKey48": 681,
    "DataCardKey5": 554,
    "DataCardKey50": 264,
    "DataCardKey50_1": 125,
    "DataCardKey51_1": 131,
    "DataCardKey52_1": 140,
    "DataCardKey55": 697,
    "DataCardKey56": 634,
    "DataCardKey6": 637,
    "DataCardKey7": 158,
    "DataCardKey8": 315,
    "DataCardKey9": 640,
    "DataCardKeyBILLpm1_1": 48,
    "DataCardKeyBILLPRpm2_1": 321,
    "DataCardKeyBUpm1_1": 27,
    "DataCardKeyBUPRpm2_1": 300,
    "DataCardKeyCLpm1_1": 39,
    "DataCardKeyCLPRpm2_1": 312,
    "DataCardKeyENpm1_1": 20,
    "DataCardKeyENPRpm2_1": 294,
    "DataCardKeyPOSpm1_1": 33,
    "DataCardKeyPOSPRpm2_1": 306,
    "DataCardKeySITEpm1_1": 23,
    "DataCardKeySITEPRpm2_1": 297,
    "DataCardKeySUpm1_1": 30,
    "DataCardKeySUPpm1_1": 51,
    "DataCardKeySUPPRpm2_1": 324,
    "DataCardKeySUPRpm2_1": 303,
    "DataCardValue2": 259,
    "DataCardValue4": 316,
    "dateEnd": 515,
    "dateNesting": 521,
    "dateOCEPHireDate": 379,
    "dateOCFPHireDate": 650,
    "dateProduction": 527,
    "dateStart": 509,
    "dpLTEffectivityDate": 621,
    "dpPREffectivityDate": 61,
    "drpOTtimezone": 530,
    "drpRosterSelection": 74,
    "EFFECTIVITY_DATE": 60,
    "EFFECTIVITY_DATE_LT": 620,
    "EffectivityDate": 332,
    "effectivityDate_card": 459,
    "effectivityDate_card_1": 209,
    "effectivityDate_input": 461,
    "effectivityDate_input_1": 211,
    "effectivityDate_label": 460,
    "effectivityDate_label_1": 210,
    "EFFECTIVITYDATE_LT": 275,
    "email_card": 441,
    "email_card_1": 191,
    "email_label": 442,
    "email_label_1": 192,
    "email_value": 443,
    "email_value_1": 193,
    "EMPLOYEE ID_Column1_1": 717,
    "EMPLOYEE ID_DataCard1": 236,
    "EMPLOYEE ID_DataCardOCFP": 633,
    "EMPLOYEE ID_LTMDataCard": 579,
    "EMPLOYEE ID_OTDataCard": 490,
    "EMPLOYEE ID_OTDataCard1": 97,
    "EMPLOYEE NAME_PRMDataCard_3": 293,
    "EmployeeGallery": 422,
    "EmployeeGallery_1": 171,
    "employeeID_1": 176,
    "EmployeeInfo_form": 428,
    "EmployeeInfo_form_1": 178,
    "employeeInfo_label": 421,
    "employeeInfo_label_1": 170,
    "employeeList_label": 420,
    "employeeList_label_1": 169,
    "employeeName": 424,
    "employeeName_1": 173,
    "EMPLOYEESTATUS_DataCard12": 664,
    "EMPLOYMENT STATUS_Column1": 725,
    "END DATE_OTDataCard": 514,
    "END DATE_OTDataCard1": 121,
    "ErrorMessage1": 619,
    "ErrorMessage2": 542,
    "ErrorMessage3": 56,
    "FIRST NAME_Column1_1": 718,
    "FIRST NAME_DataCardOCFP": 636,
    "fname_card": 429,
    "fname_card_1": 179,
    "fname_label": 430,
    "fname_label_1": 180,
    "fname_value": 431,
    "fname_value_1": 181,
    "formLTM": 578,
    "formLTM2": 235,
    "formOCFirstPage1": 632,
    "formOCFirstPage2": 651,
    "formOCFirstPage3": 670,
    "formOCFirstPage4": 689,
    "formOT": 489,
    "formOT1": 96,
    "formPREDsp2": 18,
    "formPREDsp2_1": 292,
    "FULL NAME_DataCard PRMp1_1": 19,
    "galleryLTM": 572,
    "galleryLTM_1": 229,
    "galleryLTM_2": 90,
    "galleryOT": 483,
    "galleryPRMp1st_1": 12,
    "galleryPRMp2nd_1": 286,
    "galleryTemplate2": 573,
    "galleryTemplate2_1": 230,
    "galleryTemplate2_2": 484,
    "galleryTemplate2_3": 91,
    "galleryTemplate2_4": 13,
    "galleryTemplate2_5": 287,
    "galleryTemplate3": 423,
    "galleryTemplate3_1": 172,
    "galleryTemplate6": 342,
    "galOCEP": 341,
    "grpLTSearchMultipleLOB": 627,
    "grpLTSearchMultipleOmnia": 628,
    "grpNewOCForm": 710,
    "grpOCECountry": 390,
    "grpOCEPBillability": 405,
    "grpOCEPBusUnit": 392,
    "grpOCEPButtons": 413,
    "grpOCEPCampaign": 393,
    "grpOCEPClient": 410,
    "grpOCEPEmpId": 391,
    "grpOCEPEmpStatus": 407,
    "grpOCEPFName": 394,
    "grpOCEPHireDate": 406,
    "grpOCEPInternalEmail": 409,
    "grpOCEPLName": 403,
    "grpOCEPLOB": 397,
    "grpOCEPMName": 399,
    "grpOCEPPosition": 401,
    "grpOCEPRole": 398,
    "grpOCEPRole_1": 402,
    "grpOCEPSite": 395,
    "grpOCEPStatus": 404,
    "grpOCEPSubLOB": 400,
    "grpOCEPSubUnit": 396,
    "grpOCEPSupervisor": 408,
    "grpOCFPButtons": 711,
    "grpOCSPActions": 743,
    "grpOCSPButtons": 744,
    "grpOTLOB": 562,
    "grpOTOmnia": 563,
    "grpPRSearchMultipleLOB_1": 67,
    "grpPRSearchMultipleOmnia_1": 68,
    "HIRE DATE_Column1_1": 722,
    "HIRE DATE_DataCardOCFP": 648,
    "HomePage": 69,
    "Host": 3,
    "Image2": 80,
    "INTERNAL EMAIL": 645,
    "INTERNAL EMAIL_Column1": 721,
    "INTERNSHIP_DataCard": 34,
    "INTERNSHIP_LTMDataCard": 594,
    "INTERNSHIP_PRMDataCard_2": 308,
    "Label1": 205,
    "Label10": 551,
    "Label11": 309,
    "Label12": 310,
    "Label13": 595,
    "Label14": 162,
    "Label15": 253,
    "Label16": 252,
    "Label17": 143,
    "Label18": 531,
    "Label19": 71,
    "Label19_1": 75,
    "Label2": 504,
    "Label20": 137,
    "Label21": 138,
    "Label22": 672,
    "Label23": 72,
    "Label24": 691,
    "Label25": 653,
    "Label26": 149,
    "Label27": 662,
    "Label28": 155,
    "Label29": 665,
    "Label3": 510,
    "Label30": 144,
    "Label31": 156,
    "Label32": 161,
    "Label33": 150,
    "Label34": 276,
    "Label35": 277,
    "Label36": 267,
    "Label37": 646,
    "Label38": 268,
    "Label39": 62,
    "Label4": 516,
    "Label40": 333,
    "Label41": 334,
    "Label42": 81,
    "Label42_1": 82,
    "Label43": 383,
    "Label44": 59,
    "Label45": 614,
    "Label46": 327,
    "Label47": 328,
    "Label48": 270,
    "Label49": 271,
    "Label5": 344,
    "Label5_1": 351,
    "Label5_10": 384,
    "Label5_11": 346,
    "Label5_12": 354,
    "Label5_13": 361,
    "Label5_14": 378,
    "Label5_15": 343,
    "Label5_16": 352,
    "Label5_17": 359,
    "Label5_18": 370,
    "Label5_19": 367,
    "Label5_2": 360,
    "Label5_20": 385,
    "Label5_21": 375,
    "Label5_3": 368,
    "Label5_4": 376,
    "Label5_5": 345,
    "Label5_6": 353,
    "Label5_7": 362,
    "Label5_8": 377,
    "Label5_9": 369,
    "Label50": 668,
    "Label51": 684,
    "Label52": 687,
    "Label53": 700,
    "Label54": 705,
    "Label54_1": 386,
    "Label55": 605,
    "Label56": 261,
    "Label57": 262,
    "Label58": 45,
    "Label59": 694,
    "Label6": 622,
    "Label60": 319,
    "Label61": 495,
    "Label62": 101,
    "Label63": 102,
    "Label64": 703,
    "Label65": 273,
    "Label66": 274,
    "Label67": 146,
    "Label68": 147,
    "Label69": 330,
    "Label7": 35,
    "Label70": 331,
    "Label71": 448,
    "Label73": 451,
    "Label75": 198,
    "Label76": 199,
    "Label77": 201,
    "Label78": 202,
    "Label8": 537,
    "Label9": 545,
    "LAST NAME_Column1_1": 720,
    "LAST NAME_DataCardOCFP": 642,
    "lastDate_card": 462,
    "lastDate_card_1": 212,
    "lastDate_input": 464,
    "lastDate_input_1": 214,
    "lastDate_label": 463,
    "lastDate_label_1": 213,
    "Lateral Transfer Form_1": 565,
    "Lateral Transfer Form_2": 570,
    "Lateral Transfer Form_3": 571,
    "Lateral Transfer Form_4": 226,
    "Lateral Transfer Form_5": 227,
    "Lateral Transfer Form_6": 228,
    "LateralTransfer_FirstPage": 564,
    "LateralTransfer_SecondPage": 225,
    "LineOfBusiness_Label_1": 418,
    "lname_card": 432,
    "lname_card_1": 182,
    "lname_label": 433,
    "lname_label_1": 184,
    "lname_value": 434,
    "lname_value_1": 183,
    "lob_card": 438,
    "lob_card_1": 188,
    "LOB_Column1_1": 732,
    "LOB_DataCard1": 600,
    "LOB_DataCard2": 40,
    "LOB_DataCard3": 257,
    "LOB_DataCard4": 552,
    "LOB_DataCard7": 314,
    "LOB_DataCardOCFP": 674,
    "lob_input": 417,
    "lob_label": 439,
    "lob_Label": 416,
    "lob_label_1": 190,
    "LOB_OTDataCard1": 157,
    "lob_value": 440,
    "lob_value_1": 189,
    "MIDDLE NAME_Column1_1": 719,
    "MIDDLE NAME_DataCardOCFP": 639,
    "MultipleTerminationForm_Label": 415,
    "MultipleTerminationForm_Label_1": 168,
    "NESTING START DATE_DataCard1": 520,
    "NESTING START DATE_DataCard3": 127,
    "NewHireOnboarding_EditPage": 339,
    "NewHireOnboarding_FirstPage": 629,
    "NewHireOnboarding_SecondPage": 712,
    "NextArrow2": 575,
    "NextArrow2_1": 486,
    "NextArrow2_1_Verify_1": 15,
    "NextArrow3": 232,
    "NextArrow3_1": 93,
    "NextArrow4": 425,
    "NextArrow4_2": 174,
    "NextArrow4_2_Verify_1": 289,
    "oc1": 630,
    "oc2": 713,
    "oc3": 340,
    "omnia_input": 419,
    "omniaID": 426,
    "omniaID_1": 175,
    "OT1": 476,
    "OT2": 482,
    "OT3": 481,
    "OT4": 89,
    "OT5": 88,
    "OT6": 87,
    "Others_FirstPage": 475,
    "Others_SecondPage": 86,
    "position_card": 435,
    "position_card_1": 185,
    "POSITION_Column1_1": 728,
    "POSITION_DataCard PRMp1_1": 31,
    "POSITION_DataCardOCFP": 658,
    "position_label": 436,
    "position_label_1": 186,
    "POSITION_LTMDataCard": 591,
    "POSITION_LTMDataCard2": 248,
    "POSITION_OTDataCard": 546,
    "POSITION_OTDataCard1": 151,
    "POSITION_PRMDataCard2_2": 305,
    "position_value": 437,
    "position_value_1": 187,
    "proceed_btn": 474,
    "proceed_btn_1": 224,
    "PRODUCTION DATE_DataCard1": 526,
    "PRODUCTION DATE_DataCard3": 133,
    "Promotion Form p2_1": 283,
    "Promotion Form_1": 5,
    "Promotion_FirstPage": 4,
    "Promotion_SecondPage": 282,
    "Promotion-Sub_LOB2": 317,
    "Promotion-Sub_LOB2_Label": 318,
    "rdLTMInternship": 596,
    "rdPRInternship": 36,
    "Rectangle1": 631,
    "Rectangle2": 70,
    "Rectangle3": 77,
    "Rectangle3_1": 78,
    "REGULARIZATION DATE_Column1": 723,
    "Reminder": 83,
    "Remove Button Container": 221,
    "Remove_BTN": 278,
    "Remove_Button": 335,
    "REMOVE_BUTTON": 163,
    "ROLE_Column1_1": 739,
    "ROLE_DataCardOCFP": 696,
    "Roster Update Selection": 73,
    "Save Button Container": 471,
    "Save_Button": 558,
    "SAVE_BUTTON": 63,
    "SAVE_BUTTON_LT": 623,
    "SCHEDULE_OTDataCard": 523,
    "SCHEDULE_OTDataCard1": 130,
    "Separator2": 577,
    "Separator2_1": 488,
    "Separator2_1_Verify_1": 17,
    "Separator3": 234,
    "Separator3_1": 95,
    "Separator4": 427,
    "Separator4_2": 177,
    "Separator4_2_Verify_1": 291,
    "SITE DataCard PRMp1_1": 22,
    "SITE_Column1_1": 738,
    "Site_DataCard": 690,
    "SITE_LTMDataCard": 582,
    "SITE_LTMDataCard2": 239,
    "SITE_OTDataCard": 496,
    "SITE_OTDataCard1": 103,
    "SITE_PRMDataCard_4": 296,
    "START DATE_OTDataCard": 508,
    "START DATE_OTDataCard1": 115,
    "StarVisible1": 617,
    "StarVisible2": 540,
    "StarVisible3": 54,
    "STATUS_Column1": 724,
    "STATUS_DataCardOCFP": 661,
    "STATUS_OTDataCard": 502,
    "STATUS_OTDataCard1": 109,
    "Sub-LOB": 43,
    "SUB-LOB": 260,
    "SUB-LOB_Column1_1": 733,
    "Sub-LOB_DataCard": 603,
    "SUB-LOB_DataCardOCFP": 677,
    "SUB-LOB_OTDataCard": 493,
    "SUB-LOB2_OTDataCard": 100,
    "SUB-UNIT_Column1": 727,
    "SUB-UNIT_DataCard PRMp1_1": 28,
    "SUB-UNIT_DataCardOCFP": 655,
    "SUB-UNIT_LTMDataCard": 588,
    "SUB-UNIT_LTMDataCard2": 245,
    "SUB-UNIT_OTDataCard": 505,
    "SUB-UNIT_OTDataCard1": 112,
    "SUB-UNIT_PRMDataCard2_2": 302,
    "SUPERVISOR EMP ID": 272,
    "SUPERVISOR EMP ID_Column1": 736,
    "supervisor_card": 447,
    "supervisor_card_1": 197,
    "SUPERVISOR_Column1_1": 735,
    "SUPERVISOR_DataCard PRMp1_1": 49,
    "SUPERVISOR_EMAIL": 57,
    "SUPERVISOR_EMAIL_LT": 612,
    "supervisor_emp_id": 450,
    "SUPERVISOR_EMP_ID": 145,
    "SUPERVISOR_EMP_ID_PRMDataCard": 329,
    "SUPERVISOR_LT": 266,
    "SUPERVISOR_LTMDataCard": 609,
    "SUPERVISOR_OTDataCard": 532,
    "SUPERVISOR_OTDataCard1": 139,
    "supervisor_value": 449,
    "SupervisorEmail": 326,
    "supervisorEmpID_1": 200,
    "supervisorEmpID_value": 452,
    "SUPERVISORS_EMAIL_LT": 269,
    "tblOCSP": 716,
    "TEAM_PRMDataCard2_2": 323,
    "TEAMLEADEREMP.ID_DataCard1": 615,
    "TEAMLEADEREMP.ID_DataCard2": 538,
    "TEAMLEADEREMP.ID_DataCard3": 52,
    "Termination Status Verify": 208,
    "Termination_FirstPage": 414,
    "Termination_VerificationPage": 167,
    "terminationStatus_card": 456,
    "terminationStatus_card_1": 206,
    "terminationStatus_cb": 458,
    "terminationStatus_label": 457,
    "terminationStatus_label_1": 207,
    "terminationType_card": 453,
    "terminationType_card_1": 203,
    "terminationType_cb": 455,
    "terminationType_label": 454,
    "terminationType_label_1": 204,
    "Time_Zone": 529,
    "TIME_ZONE": 136,
    "trainer1": 536,
    "Trainer1": 142,
    "TRAINER1": 535,
    "trainer2": 544,
    "Trainer2": 148,
    "TRAINER2": 543,
    "trainer3": 550,
    "Trainer3": 154,
    "TRAINER3": 549,
    "Treehouse Guide Group": 85,
    "txtLTMultipleBillability2": 265,
    "txtLTMultipleBusUnit2": 244,
    "txtLTMultipleEmpId": 581,
    "txtLTMultipleEmpId2": 238,
    "txtLTMultipleName": 574,
    "txtLTMultipleName_1": 231,
    "txtLTMultipleName_2": 92,
    "txtLTMultipleName_3": 288,
    "txtLTMultipleOmnia": 576,
    "txtLTMultipleOmnia_1": 233,
    "txtLTMultipleOmnia_2": 94,
    "txtLTMultiplePosition2": 250,
    "txtLTMultipleSite": 584,
    "txtLTMultipleSite2": 241,
    "txtLTMultipleSubUnit2": 247,
    "txtLTMutipleClient2": 256,
    "txtLTSearchMultipleLOB": 566,
    "txtLTSearchMultipleOmnia": 569,
    "txtOCEPClassName": 382,
    "txtOCEPEmpId": 348,
    "txtOCEPFName": 356,
    "txtOCEPInternalEmail": 387,
    "txtOCEPLName": 372,
    "txtOCEPMName": 364,
    "txtOCEPSupervisorEmpID": 389,
    "txtOCFPClassName": 704,
    "txtOCFPEmpId": 635,
    "txtOCFPFName": 638,
    "txtOCFPLName": 644,
    "txtOCFPMName": 641,
    "txtOCFPSupervisorEmpId": 688,
    "txtOCInternalEmail": 647,
    "txtOTBillability1": 126,
    "txtOTBusUnit1": 108,
    "txtOTClient1": 120,
    "txtOTEmpId": 492,
    "txtOTEmpId1": 99,
    "txtOTEndDate1": 123,
    "txtOTLOB": 478,
    "txtOTLOB1": 159,
    "txtOTMName": 485,
    "txtOTMOmnia": 487,
    "txtOTNesting1": 129,
    "txtOTOmnia": 480,
    "txtOTPosition1": 153,
    "txtOTProduction1": 135,
    "txtOTSchedule": 524,
    "txtOTSchedule1": 132,
    "txtOTSite": 498,
    "txtOTSite1": 105,
    "txtOTStartdate1": 117,
    "txtOTStatus1": 111,
    "txtOTSubUnit1": 114,
    "txtOTSupervisor1": 141,
    "txtPREDp1_1": 11,
    "txtPREDp2_1": 285,
    "txtPRMultipleBILLpm2_1": 322,
    "txtPRMultipleBUpm2_1": 301,
    "txtPRMultipleCLpm2_1": 313,
    "txtPRMultipleEmpName_1": 21,
    "txtPRMultipleEmpNamepm2_1": 295,
    "txtPRMultipleNamepm1_1": 14,
    "txtPRMultipleOmniapm1": 16,
    "txtPRMultipleOmniapm2_1": 290,
    "txtPRMultiplePOSpm2_1": 307,
    "txtPRMultipleSite_1": 24,
    "txtPRMultipleSitepm2_1": 298,
    "txtPRMultipleSUpm2_1": 304,
    "txtPRMultipleSUPpm2_1": 325,
    "txtPRSearchMultipleLOB_1": 6,
    "txtPRSearchMultipleOmnia_1": 9,
    "txtPRSEp1_1": 10,
    "txtPRUEp2_1": 284
  },
  "FunctionParamsInvariantScripts": {},
  "FunctionParamsInvariantScriptsOnInstances": {},
  "HeaderLastSavedDateTimeUTC": "03/05/2024 20:52:50",
  "IsLegacyComponentAllowGlobalScopeCase": false,
  "LocalConnectionIDReferences": {
    "10a6e1dd-d18a-4264-ba6a-c6168d122955": "\"/providers/microsoft.powerapps/apis/shared_logicflows/connections/c04e8e8ecc0f4a81a3e377c930025dc4-f1c323350ee50a3a\"",
    "445c2806-6ace-410f-adcf-5edfa6f6c6cb": "\"/providers/microsoft.powerapps/apis/shared_excelonlinebusiness/connections/e8057648d5254ded85eabac86900a71e\"",
    "63907533-31f8-4115-b263-da6a3db293f3": "\"/providers/microsoft.powerapps/apis/shared_logicflows/connections/8d71eb372a62403e910a072ebf0f00f4-f1c323350ee50a3a\"",
    "a8e87f65-9406-41aa-ab47-b853dbf0de2d": "\"/providers/microsoft.powerapps/apis/shared_logicflows/connections/110487544e584ab0ab425a0db8a96338-ed4dc2137967c9c7\"",
    "a98f1ce0-65af-4442-ad24-7697c24f3724": "\"/providers/microsoft.powerapps/apis/shared_office365/connections/62bfa946d73f4bf1b4c5d4b4c842edfb\"",
    "ae060470-fd62-4be7-b9f1-2bbad2948a8e": "\"/providers/microsoft.powerapps/apis/shared_logicflows/connections/d718e933082e42fca3b53c1125ff80df-f1c323350ee50a3a\"",
    "f001c07c-733c-47b5-9cc0-afa32cdc09de": "\"/providers/microsoft.powerapps/apis/shared_sharepointonline/connections/9a1322d96bcf422b8b9c4a9d917e14d4\"",
    "f22ee5e0-92b8-4e48-9853-081a22bf95fe": "\"/providers/microsoft.powerapps/apis/shared_logicflows/connections/6937b00b47884d508f52051066369d1e-f1c323350ee50a3a\""
  },
  "LocalDatabaseReferencesAsEmpty": true,
  "LocalResourceFileNames": {
    "bit.ly_CSFreshService": "4899ac47-87d7-40f1-9936-d68396123f4c.png",
    "bit.ly_DynamicRosterUpdateApplication-Treehouse": "9067cb6b-839b-4058-95bd-2eb00d298c02.png",
    "homeScreen": "83ae0a84-050f-4954-af53-4824d9d7e624.png",
    "homeScreen2": "f3221eef-2964-4bea-bdec-75bd42bdf521.png",
    "MicrosoftTeams-image": "7886b3c1-9983-4892-a2e5-cec6afa3fa41.png",
    "MicrosoftTeams-image (2)": "f781a3c3-d213-4099-acf4-9844bd2d1c6a.png",
    "Untitled design 29": "978392d2-fc92-4e8f-a15e-6aa4c499d7d4.png"
  },
  "LocalResourceRootPaths": {
    "bit.ly_CSFreshService": "https://docserverpwaprodwus.blob.core.windows.net/1b17c9db-d3e7-4de4-abd7-fcb501cd3c79-1/resource/Assets0Images04899ac47-87d7-40f1-9936-d68396123f4c.png?skoid=58690ece-ec83-4ce2-9ce8-883d4d6a54ee&sktid=975f013f-7f24-47e8-a7d3-abc4752bf346&skt=2024-03-05T20%3A51%3A20Z&ske=2024-03-06T21%3A06%3A20Z&sks=b&skv=2022-11-02&sv=2022-11-02&spr=https&se=2024-03-06T21%3A06%3A20Z&sr=b&sp=r&sig=KPTrFMh6S6DIBpxXoxYYRFMAPjYlGVOG0y5jVMqthV4%3D",
    "bit.ly_DynamicRosterUpdateApplication-Treehouse": "https://docserverpwaprodwus.blob.core.windows.net/1b17c9db-d3e7-4de4-abd7-fcb501cd3c79-1/resource/Assets0Images09067cb6b-839b-4058-95bd-2eb00d298c02.png?skoid=58690ece-ec83-4ce2-9ce8-883d4d6a54ee&sktid=975f013f-7f24-47e8-a7d3-abc4752bf346&skt=2024-03-05T20%3A51%3A20Z&ske=2024-03-06T21%3A06%3A20Z&sks=b&skv=2022-11-02&sv=2022-11-02&spr=https&se=2024-03-06T21%3A06%3A20Z&sr=b&sp=r&sig=SWH9g4G%2FIsZhGL8ymarza1AeVzpTAQvQLtp8sfQ5Omc%3D",
    "homeScreen": "https://docserverpwaprodwus.blob.core.windows.net/1b17c9db-d3e7-4de4-abd7-fcb501cd3c79-1/resource/Assets0Images083ae0a84-050f-4954-af53-4824d9d7e624.png?skoid=58690ece-ec83-4ce2-9ce8-883d4d6a54ee&sktid=975f013f-7f24-47e8-a7d3-abc4752bf346&skt=2024-03-05T20%3A51%3A20Z&ske=2024-03-06T21%3A06%3A20Z&sks=b&skv=2022-11-02&sv=2022-11-02&spr=https&se=2024-03-06T21%3A06%3A20Z&sr=b&sp=r&sig=t2e39KOEcUjvQaP2LuTSFECrkBoIR8dorQa0r0fujsc%3D",
    "homeScreen2": "https://docserverpwaprodwus.blob.core.windows.net/1b17c9db-d3e7-4de4-abd7-fcb501cd3c79-1/resource/Assets0Images0f3221eef-2964-4bea-bdec-75bd42bdf521.png?skoid=58690ece-ec83-4ce2-9ce8-883d4d6a54ee&sktid=975f013f-7f24-47e8-a7d3-abc4752bf346&skt=2024-03-05T20%3A51%3A20Z&ske=2024-03-06T21%3A06%3A20Z&sks=b&skv=2022-11-02&sv=2022-11-02&spr=https&se=2024-03-06T21%3A06%3A20Z&sr=b&sp=r&sig=n5zJsqhzVXO1wCmMO1CQrSZS5FFuQTNBJJYxiothIDs%3D",
    "MicrosoftTeams-image": "https://docserverpwaprodwus.blob.core.windows.net/1b17c9db-d3e7-4de4-abd7-fcb501cd3c79-1/resource/Assets0Images07886b3c1-9983-4892-a2e5-cec6afa3fa41.png?skoid=58690ece-ec83-4ce2-9ce8-883d4d6a54ee&sktid=975f013f-7f24-47e8-a7d3-abc4752bf346&skt=2024-03-05T20%3A51%3A20Z&ske=2024-03-06T21%3A06%3A20Z&sks=b&skv=2022-11-02&sv=2022-11-02&spr=https&se=2024-03-06T21%3A06%3A20Z&sr=b&sp=r&sig=lBvLy2AYRh6AnooUg4Siy505FNU5c3FT2PAI8qcmVQQ%3D",
    "MicrosoftTeams-image (2)": "https://docserverpwaprodwus.blob.core.windows.net/1b17c9db-d3e7-4de4-abd7-fcb501cd3c79-1/resource/Assets0Images0f781a3c3-d213-4099-acf4-9844bd2d1c6a.png?skoid=58690ece-ec83-4ce2-9ce8-883d4d6a54ee&sktid=975f013f-7f24-47e8-a7d3-abc4752bf346&skt=2024-03-05T20%3A51%3A20Z&ske=2024-03-06T21%3A06%3A20Z&sks=b&skv=2022-11-02&sv=2022-11-02&spr=https&se=2024-03-06T21%3A06%3A20Z&sr=b&sp=r&sig=yA0FtdXhb3AS0b0vN8piIqG46e6F1XHgIVgV4flm4TA%3D",
    "Untitled design 29": "https://docserverpwaprodwus.blob.core.windows.net/1b17c9db-d3e7-4de4-abd7-fcb501cd3c79-1/resource/Assets0Images0978392d2-fc92-4e8f-a15e-6aa4c499d7d4.png?skoid=58690ece-ec83-4ce2-9ce8-883d4d6a54ee&sktid=975f013f-7f24-47e8-a7d3-abc4752bf346&skt=2024-03-05T20%3A51%3A20Z&ske=2024-03-06T21%3A06%3A20Z&sks=b&skv=2022-11-02&sv=2022-11-02&spr=https&se=2024-03-06T21%3A06%3A20Z&sr=b&sp=r&sig=jCuMzj%2Fx3c9kUE8DdFJ9QhI7TS0iOv6UcXzrBqzqIcA%3D"
  },
  "OldLogoFileName": "mlxmmrgs.jpg",
  "OrderComponentMetadata": {},
  "OrderComponentTemplate": {},
  "OrderDataSource": {
    "colLateralTransfer": 11,
    "colOldLOB": 16,
    "colOmniaCreation": 15,
    "colOROldLOB": 19,
    "colOthers": 12,
    "colPROldLOB": 18,
    "colPromotion": 14,
    "colTROldLOB": 17,
    "ComboBoxSample": 6,
    "CustomGallerySample": 7,
    "DEV-Lateral_Transfer": 4,
    "DEV-New_Hire_Onboarding": 5,
    "DEV-Other_Roster_Update": 3,
    "DEV-Promotion": 1,
    "DEV-Termination": 2,
    "DropDownSample": 8,
    "Headcount_table": 10,
    "Office365Outlook": 0,
    "RadioSample": 9,
    "userVerify": 13
  },
  "OrderGroupControls": {
    "CS FreshService Group": {
      "CS FreshService": 1,
      "Label42": 0,
      "Rectangle3": 2
    },
    "grpLTSearchMultipleLOB": {
      "cbLTSearchMultipleLOB": 1,
      "txtLTSearchMultipleLOB": 0
    },
    "grpLTSearchMultipleOmnia": {
      "cbLTSearchMultipleOmnia": 0,
      "txtLTSearchMultipleOmnia": 1
    },
    "grpNewOCForm": {
      "formOCFirstPage1": 3,
      "formOCFirstPage2": 2,
      "formOCFirstPage3": 1,
      "formOCFirstPage4": 0
    },
    "grpOCECountry": {
      "cbOCEPCountry": 0,
      "Label5_15": 1
    },
    "grpOCEPBillability": {
      "cbOCEPBillability": 1,
      "Label5_18": 0
    },
    "grpOCEPBusUnit": {
      "cbOCEPBusUnit": 0,
      "Label5_5": 1
    },
    "grpOCEPButtons": {
      "btnOCEPBack": 0,
      "btnOCEPUpdate": 1
    },
    "grpOCEPCampaign": {
      "cbOCEPCampaign": 0,
      "Label5_11": 1
    },
    "grpOCEPClient": {
      "cbOCEPClient": 0,
      "Label5_10": 1
    },
    "grpOCEPEmpId": {
      "Label5": 1,
      "txtOCEPEmpId": 0
    },
    "grpOCEPEmpStatus": {
      "cbOCEPEmpStatus": 1,
      "Label5_8": 0
    },
    "grpOCEPFName": {
      "Label5_1": 1,
      "txtOCEPFName": 0
    },
    "grpOCEPHireDate": {
      "dateOCEPHireDate": 1,
      "Label5_4": 0
    },
    "grpOCEPInternalEmail": {
      "Label43": 0,
      "txtOCEPInternalEmail": 1
    },
    "grpOCEPLName": {
      "Label5_3": 0,
      "txtOCEPLName": 1
    },
    "grpOCEPLOB": {
      "cbOCEPLOB": 0,
      "Label5_12": 1
    },
    "grpOCEPMName": {
      "Label5_2": 0,
      "txtOCEPMName": 1
    },
    "grpOCEPPosition": {
      "cbOCEPPosition": 0,
      "Label5_7": 1
    },
    "grpOCEPRole": {
      "cbOCEPRole": 1,
      "Label5_17": 0
    },
    "grpOCEPRole_1": {
      "cbOCEPAlvariaID": 1,
      "Label5_19": 0
    },
    "grpOCEPSite": {
      "cbOCEPSite": 0,
      "Label5_16": 1
    },
    "grpOCEPStatus": {
      "cbOCEPStatus": 0,
      "Label5_9": 1
    },
    "grpOCEPSubLOB": {
      "cbOCEPSubLOB": 1,
      "Label5_13": 0
    },
    "grpOCEPSubUnit": {
      "cbOCEPSubUnit": 0,
      "Label5_6": 1
    },
    "grpOCEPSupervisor": {
      "cbOCEPSupervisor": 0,
      "Label5_14": 1
    },
    "grpOCFPButtons": {
      "btnOCFPBack": 0,
      "btnOCFPReview": 1
    },
    "grpOCSPActions": {
      "btnOCSPEdit": 0,
      "btnOCSPRemove": 1
    },
    "grpOCSPButtons": {
      "btnOCSPBack": 0,
      "btnOCSPSubmit": 1
    },
    "grpOTLOB": {
      "cbOTSearchLOB": 1,
      "txtOTLOB": 0
    },
    "grpOTOmnia": {
      "cbOTOmnia": 0,
      "txtOTOmnia": 1
    },
    "grpPRSearchMultipleLOB_1": {
      "cbPRSearchMultipleLOB": 1,
      "txtPRSearchMultipleLOB_1": 0
    },
    "grpPRSearchMultipleOmnia_1": {
      "cbPRSearchMultipleOmnia": 0,
      "txtPRSearchMultipleOmnia_1": 1
    },
    "Reminder": {
      "Label19": 0,
      "Label23": 1,
      "Rectangle2": 2
    },
    "Treehouse Guide Group": {
      "Image2": 2,
      "Label42_1": 0,
      "Rectangle3_1": 1
    }
  },
  "OrderPcfTemplate": {},
  "OrderTemplate": {},
  "OrderXMLTemplate": {
    "button": 9,
    "combobox": 1,
    "datepicker": 8,
    "dropdown": 10,
    "form": 5,
    "gallery": 2,
    "htmlViewer": 12,
    "icon": 3,
    "image": 11,
    "label": 0,
    "radio": 6,
    "rectangle": 4,
    "text": 7
  },
  "OverridablePropertiesEntry": {
    "address_card": {},
    "address_card_1": {},
    "address_input": {},
    "address_input_1": {},
    "address_label": {},
    "address_label_1": {},
    "ALVARIA ID_Column1": {},
    "Alvaria_ID": {},
    "App": {},
    "BILLABILITY_Column1_1": {},
    "BILLABILITY_DataCard PRMp1_1": {},
    "BILLABILITY_DataCardOCFP": {},
    "BILLABILITY_LTMDataCard": {},
    "BILLABILITY_LTMDataCard2": {},
    "BILLABILITY_OTDataCard": {},
    "BILLABILITY_OTDataCard1": {},
    "BILLABILITY_PRMDataCard2_2": {},
    "btnFirstPageNext": {},
    "btnLTMultipleBack": {},
    "btnLTMultipleBack_1": {},
    "btnLTMultipleBack_2": {},
    "btnLTMultipleBack_3": {},
    "btnLTMultipleBack_4": {},
    "btnLTMultipleReview": {},
    "btnLTMultipleReview_1": {},
    "btnLTMultipleReview_2": {},
    "btnLTRemove": {},
    "btnLTRemove_1": {},
    "btnOCEPBack": {},
    "btnOCEPUpdate": {},
    "btnOCFPBack": {},
    "btnOCFPReview": {},
    "btnOCFPSave": {},
    "btnOCSPBack": {},
    "btnOCSPEdit": {},
    "btnOCSPRemove": {},
    "btnOCSPSubmit": {},
    "btnOTBack": {},
    "btnOTRemove": {},
    "btnOTReview": {},
    "btnOTSave": {},
    "btnPRMultipleBackp1_1": {},
    "btnPRMultipleBackp2_1": {},
    "btnPRMultipleReviewp1_1": {},
    "btnPRMultipleSubmitp2_1": {},
    "btnPRRemovep2_3": {},
    "BUSINESS UNIT_Column1_1": {},
    "BUSINESS UNIT_DataCard PRMp1_1": {},
    "BUSINESS UNIT_DataCardOCFP": {},
    "BUSINESS UNIT_LTMDataCard": {},
    "BUSINESS UNIT_LTMDataCard2": {},
    "BUSINESS UNIT_OTDataCard": {},
    "BUSINESS UNIT_OTDataCard1": {},
    "BUSINESS UNIT_PRMDataCard_4": {},
    "Button1": {},
    "Button2": {},
    "Button5": {},
    "Button6": {},
    "campaign_card": {},
    "campaign_card_1": {},
    "CAMPAIGN_Column1_1": {},
    "campaign_label": {},
    "campaign_label_1": {},
    "campaign_value": {},
    "campaign_value_1": {},
    "cbLTMultipleBillability": {},
    "cbLTMultipleBusUnit": {},
    "cbLTMultipleClient": {},
    "cbLTMultipleLOB": {},
    "cbLTMultiplePosition": {},
    "cbLTMultipleSubLOB": {},
    "cbLTMultipleSubUnit": {},
    "cbLTMultipleSupervisor": {},
    "cbLTMultipleSupervisorEmail_1": {},
    "cbLTMultipleSupervisorEmpID_1": {},
    "cbLTSearchMultipleLOB": {},
    "cbLTSearchMultipleOmnia": {},
    "cbOCEPAlvariaID": {},
    "cbOCEPBillability": {},
    "cbOCEPBusUnit": {},
    "cbOCEPCampaign": {},
    "cbOCEPClient": {},
    "cbOCEPCountry": {},
    "cbOCEPEmpStatus": {},
    "cbOCEPLOB": {},
    "cbOCEPPosition": {},
    "cbOCEPRole": {},
    "cbOCEPSite": {},
    "cbOCEPStatus": {},
    "cbOCEPSubLOB": {},
    "cbOCEPSubUnit": {},
    "cbOCEPSupervisor": {},
    "cbOCFPAlvariaID": {},
    "cbOCFPBillability": {},
    "cbOCFPBusUnit": {},
    "cbOCFPClient": {},
    "cbOCFPCountry": {},
    "cbOCFPDivision": {},
    "cbOCFPEmpStatus": {},
    "cbOCFPLOB": {},
    "cbOCFPPosition": {},
    "cbOCFPRole": {},
    "cbOCFPSite": {},
    "cbOCFPStatus": {},
    "cbOCFPSubLOB": {},
    "cbOCFPSubUnit": {},
    "cbOCFPSupervisor": {},
    "cbOTBillability": {},
    "cbOTBusUnit": {},
    "cbOTClient": {},
    "cbOTLOB": {},
    "cbOTOmnia": {},
    "cbOTPosition": {},
    "cbOTSearchLOB": {},
    "cbOTStatus": {},
    "cbOTSub-LOB": {},
    "cbOTSubUnit": {},
    "cbOTSupervisor": {},
    "cbOTSupervisorEmpID": {},
    "cbPRMultipleBillability_1": {},
    "cbPRMultipleBusUnit_1": {},
    "cbPRMultipleClient_1": {},
    "cbPRMultipleLOB_2": {},
    "cbPRMultiplePosition_1": {},
    "cbPRMultipleSub-LOB": {},
    "cbPRMultipleSubUnit_1": {},
    "cbPRMultipleSupervisor_1": {},
    "cbPRMultipleSupervisorEmail_1": {},
    "cbPRMultipleSupervisorEmpID_1": {},
    "cbPRSearchMultipleLOB": {},
    "cbPRSearchMultipleOmnia": {},
    "CLASS NAME_Column1": {},
    "class_name": {},
    "Class_Name": {},
    "CLASS_NAME": {},
    "ClassName": {},
    "CLIENT_Column1_1": {},
    "CLIENT_DataCard PRMp1_1": {},
    "CLIENT_LTMDataCard": {},
    "CLIENT_LTMDataCard2": {},
    "CLIENT_OTDataCard": {},
    "CLIENT_OTDataCard1": {},
    "CLIENT_PRMDataCard2_2": {},
    "comment_card": {},
    "comment_card_1": {},
    "comment_input": {},
    "comment_input_1": {},
    "comment_label": {},
    "comment_label_1": {},
    "COUNTRY_Column1_1": {},
    "Country_DataCard": {},
    "Country_DataCard1": {},
    "CS FreshService": {},
    "CS FreshService Group": {},
    "DataCard10": {},
    "DataCard2": {},
    "DataCard3": {},
    "DataCard7": {},
    "DataCard8": {},
    "DataCardKey1": {},
    "DataCardKey1_1": {},
    "DataCardKey10": {},
    "DataCardKey11": {},
    "DataCardKey12": {},
    "DataCardKey13": {},
    "DataCardKey14": {},
    "DataCardKey15": {},
    "DataCardKey15_1": {},
    "DataCardKey16": {},
    "DataCardKey16_1": {},
    "DataCardKey18": {},
    "DataCardKey19": {},
    "DataCardKey2": {},
    "DataCardKey24": {},
    "DataCardKey24_1": {},
    "DataCardKey27": {},
    "DataCardKey28": {},
    "DataCardKey29": {},
    "DataCardKey3": {},
    "DataCardKey35": {},
    "DataCardKey36": {},
    "DataCardKey36_1": {},
    "DataCardKey37": {},
    "DataCardKey37_1": {},
    "DataCardKey37_2": {},
    "DataCardKey37_3": {},
    "DataCardKey38": {},
    "DataCardKey38_1": {},
    "DataCardKey39": {},
    "DataCardKey39_1": {},
    "DataCardKey4": {},
    "DataCardKey40": {},
    "DataCardKey40_1": {},
    "DataCardKey41": {},
    "DataCardKey41_1": {},
    "DataCardKey42": {},
    "DataCardKey42_1": {},
    "DataCardKey43_1": {},
    "DataCardKey44": {},
    "DataCardKey44_1": {},
    "DataCardKey45": {},
    "DataCardKey45_1": {},
    "DataCardKey46": {},
    "DataCardKey47": {},
    "DataCardKey47_1": {},
    "DataCardKey47_2": {},
    "DataCardKey47_3": {},
    "DataCardKey48": {},
    "DataCardKey5": {},
    "DataCardKey50": {},
    "DataCardKey50_1": {},
    "DataCardKey51_1": {},
    "DataCardKey52_1": {},
    "DataCardKey55": {},
    "DataCardKey56": {},
    "DataCardKey6": {},
    "DataCardKey7": {},
    "DataCardKey8": {},
    "DataCardKey9": {},
    "DataCardKeyBILLpm1_1": {},
    "DataCardKeyBILLPRpm2_1": {},
    "DataCardKeyBUpm1_1": {},
    "DataCardKeyBUPRpm2_1": {},
    "DataCardKeyCLpm1_1": {},
    "DataCardKeyCLPRpm2_1": {},
    "DataCardKeyENpm1_1": {},
    "DataCardKeyENPRpm2_1": {},
    "DataCardKeyPOSpm1_1": {},
    "DataCardKeyPOSPRpm2_1": {},
    "DataCardKeySITEpm1_1": {},
    "DataCardKeySITEPRpm2_1": {},
    "DataCardKeySUpm1_1": {},
    "DataCardKeySUPpm1_1": {},
    "DataCardKeySUPPRpm2_1": {},
    "DataCardKeySUPRpm2_1": {},
    "DataCardValue2": {},
    "DataCardValue4": {},
    "dateEnd": {},
    "dateNesting": {},
    "dateOCEPHireDate": {},
    "dateOCFPHireDate": {},
    "dateProduction": {},
    "dateStart": {},
    "dpLTEffectivityDate": {},
    "dpPREffectivityDate": {},
    "drpOTtimezone": {},
    "drpRosterSelection": {},
    "EFFECTIVITY_DATE": {},
    "EFFECTIVITY_DATE_LT": {},
    "EffectivityDate": {},
    "effectivityDate_card": {},
    "effectivityDate_card_1": {},
    "effectivityDate_input": {},
    "effectivityDate_input_1": {},
    "effectivityDate_label": {},
    "effectivityDate_label_1": {},
    "EFFECTIVITYDATE_LT": {},
    "email_card": {},
    "email_card_1": {},
    "email_label": {},
    "email_label_1": {},
    "email_value": {},
    "email_value_1": {},
    "EMPLOYEE ID_Column1_1": {},
    "EMPLOYEE ID_DataCard1": {},
    "EMPLOYEE ID_DataCardOCFP": {},
    "EMPLOYEE ID_LTMDataCard": {},
    "EMPLOYEE ID_OTDataCard": {},
    "EMPLOYEE ID_OTDataCard1": {},
    "EMPLOYEE NAME_PRMDataCard_3": {},
    "EmployeeGallery": {},
    "EmployeeGallery_1": {},
    "employeeID_1": {},
    "EmployeeInfo_form": {},
    "EmployeeInfo_form_1": {},
    "employeeInfo_label": {},
    "employeeInfo_label_1": {},
    "employeeList_label": {},
    "employeeList_label_1": {},
    "employeeName": {},
    "employeeName_1": {},
    "EMPLOYEESTATUS_DataCard12": {},
    "EMPLOYMENT STATUS_Column1": {},
    "END DATE_OTDataCard": {},
    "END DATE_OTDataCard1": {},
    "ErrorMessage1": {},
    "ErrorMessage2": {},
    "ErrorMessage3": {},
    "FIRST NAME_Column1_1": {},
    "FIRST NAME_DataCardOCFP": {},
    "fname_card": {},
    "fname_card_1": {},
    "fname_label": {},
    "fname_label_1": {},
    "fname_value": {},
    "fname_value_1": {},
    "formLTM": {},
    "formLTM2": {},
    "formOCFirstPage1": {},
    "formOCFirstPage2": {},
    "formOCFirstPage3": {},
    "formOCFirstPage4": {},
    "formOT": {},
    "formOT1": {},
    "formPREDsp2": {},
    "formPREDsp2_1": {},
    "FULL NAME_DataCard PRMp1_1": {},
    "galleryLTM": {},
    "galleryLTM_1": {},
    "galleryLTM_2": {},
    "galleryOT": {},
    "galleryPRMp1st_1": {},
    "galleryPRMp2nd_1": {},
    "galleryTemplate2": {},
    "galleryTemplate2_1": {},
    "galleryTemplate2_2": {},
    "galleryTemplate2_3": {},
    "galleryTemplate2_4": {},
    "galleryTemplate2_5": {},
    "galleryTemplate3": {},
    "galleryTemplate3_1": {},
    "galleryTemplate6": {},
    "galOCEP": {},
    "grpLTSearchMultipleLOB": {},
    "grpLTSearchMultipleOmnia": {},
    "grpNewOCForm": {},
    "grpOCECountry": {},
    "grpOCEPBillability": {},
    "grpOCEPBusUnit": {},
    "grpOCEPButtons": {},
    "grpOCEPCampaign": {},
    "grpOCEPClient": {},
    "grpOCEPEmpId": {},
    "grpOCEPEmpStatus": {},
    "grpOCEPFName": {},
    "grpOCEPHireDate": {},
    "grpOCEPInternalEmail": {},
    "grpOCEPLName": {},
    "grpOCEPLOB": {},
    "grpOCEPMName": {},
    "grpOCEPPosition": {},
    "grpOCEPRole": {},
    "grpOCEPRole_1": {},
    "grpOCEPSite": {},
    "grpOCEPStatus": {},
    "grpOCEPSubLOB": {},
    "grpOCEPSubUnit": {},
    "grpOCEPSupervisor": {},
    "grpOCFPButtons": {},
    "grpOCSPActions": {},
    "grpOCSPButtons": {},
    "grpOTLOB": {},
    "grpOTOmnia": {},
    "grpPRSearchMultipleLOB_1": {},
    "grpPRSearchMultipleOmnia_1": {},
    "HIRE DATE_Column1_1": {},
    "HIRE DATE_DataCardOCFP": {},
    "HomePage": {},
    "Host": {},
    "Image2": {},
    "INTERNAL EMAIL": {},
    "INTERNAL EMAIL_Column1": {},
    "INTERNSHIP_DataCard": {},
    "INTERNSHIP_LTMDataCard": {},
    "INTERNSHIP_PRMDataCard_2": {},
    "Label1": {},
    "Label10": {},
    "Label11": {},
    "Label12": {},
    "Label13": {},
    "Label14": {},
    "Label15": {},
    "Label16": {},
    "Label17": {},
    "Label18": {},
    "Label19": {},
    "Label19_1": {},
    "Label2": {},
    "Label20": {},
    "Label21": {},
    "Label22": {},
    "Label23": {},
    "Label24": {},
    "Label25": {},
    "Label26": {},
    "Label27": {},
    "Label28": {},
    "Label29": {},
    "Label3": {},
    "Label30": {},
    "Label31": {},
    "Label32": {},
    "Label33": {},
    "Label34": {},
    "Label35": {},
    "Label36": {},
    "Label37": {},
    "Label38": {},
    "Label39": {},
    "Label4": {},
    "Label40": {},
    "Label41": {},
    "Label42": {},
    "Label42_1": {},
    "Label43": {},
    "Label44": {},
    "Label45": {},
    "Label46": {},
    "Label47": {},
    "Label48": {},
    "Label49": {},
    "Label5": {},
    "Label5_1": {},
    "Label5_10": {},
    "Label5_11": {},
    "Label5_12": {},
    "Label5_13": {},
    "Label5_14": {},
    "Label5_15": {},
    "Label5_16": {},
    "Label5_17": {},
    "Label5_18": {},
    "Label5_19": {},
    "Label5_2": {},
    "Label5_20": {},
    "Label5_21": {},
    "Label5_3": {},
    "Label5_4": {},
    "Label5_5": {},
    "Label5_6": {},
    "Label5_7": {},
    "Label5_8": {},
    "Label5_9": {},
    "Label50": {},
    "Label51": {},
    "Label52": {},
    "Label53": {},
    "Label54": {},
    "Label54_1": {},
    "Label55": {},
    "Label56": {},
    "Label57": {},
    "Label58": {},
    "Label59": {},
    "Label6": {},
    "Label60": {},
    "Label61": {},
    "Label62": {},
    "Label63": {},
    "Label64": {},
    "Label65": {},
    "Label66": {},
    "Label67": {},
    "Label68": {},
    "Label69": {},
    "Label7": {},
    "Label70": {},
    "Label71": {},
    "Label73": {},
    "Label75": {},
    "Label76": {},
    "Label77": {},
    "Label78": {},
    "Label8": {},
    "Label9": {},
    "LAST NAME_Column1_1": {},
    "LAST NAME_DataCardOCFP": {},
    "lastDate_card": {},
    "lastDate_card_1": {},
    "lastDate_input": {},
    "lastDate_input_1": {},
    "lastDate_label": {},
    "lastDate_label_1": {},
    "Lateral Transfer Form_1": {},
    "Lateral Transfer Form_2": {},
    "Lateral Transfer Form_3": {},
    "Lateral Transfer Form_4": {},
    "Lateral Transfer Form_5": {},
    "Lateral Transfer Form_6": {},
    "LateralTransfer_FirstPage": {},
    "LateralTransfer_SecondPage": {},
    "LineOfBusiness_Label_1": {},
    "lname_card": {},
    "lname_card_1": {},
    "lname_label": {},
    "lname_label_1": {},
    "lname_value": {},
    "lname_value_1": {},
    "lob_card": {},
    "lob_card_1": {},
    "LOB_Column1_1": {},
    "LOB_DataCard1": {},
    "LOB_DataCard2": {},
    "LOB_DataCard3": {},
    "LOB_DataCard4": {},
    "LOB_DataCard7": {},
    "LOB_DataCardOCFP": {},
    "lob_input": {},
    "lob_label": {},
    "lob_Label": {},
    "lob_label_1": {},
    "LOB_OTDataCard1": {},
    "lob_value": {},
    "lob_value_1": {},
    "MIDDLE NAME_Column1_1": {},
    "MIDDLE NAME_DataCardOCFP": {},
    "MultipleTerminationForm_Label": {},
    "MultipleTerminationForm_Label_1": {},
    "NESTING START DATE_DataCard1": {},
    "NESTING START DATE_DataCard3": {},
    "NewHireOnboarding_EditPage": {},
    "NewHireOnboarding_FirstPage": {},
    "NewHireOnboarding_SecondPage": {},
    "NextArrow2": {},
    "NextArrow2_1": {},
    "NextArrow2_1_Verify_1": {},
    "NextArrow3": {},
    "NextArrow3_1": {},
    "NextArrow4": {},
    "NextArrow4_2": {},
    "NextArrow4_2_Verify_1": {},
    "oc1": {},
    "oc2": {},
    "oc3": {},
    "omnia_input": {},
    "omniaID": {},
    "omniaID_1": {},
    "OT1": {},
    "OT2": {},
    "OT3": {},
    "OT4": {},
    "OT5": {},
    "OT6": {},
    "Others_FirstPage": {},
    "Others_SecondPage": {},
    "position_card": {},
    "position_card_1": {},
    "POSITION_Column1_1": {},
    "POSITION_DataCard PRMp1_1": {},
    "POSITION_DataCardOCFP": {},
    "position_label": {},
    "position_label_1": {},
    "POSITION_LTMDataCard": {},
    "POSITION_LTMDataCard2": {},
    "POSITION_OTDataCard": {},
    "POSITION_OTDataCard1": {},
    "POSITION_PRMDataCard2_2": {},
    "position_value": {},
    "position_value_1": {},
    "proceed_btn": {},
    "proceed_btn_1": {},
    "PRODUCTION DATE_DataCard1": {},
    "PRODUCTION DATE_DataCard3": {},
    "Promotion Form p2_1": {},
    "Promotion Form_1": {},
    "Promotion_FirstPage": {},
    "Promotion_SecondPage": {},
    "Promotion-Sub_LOB2": {},
    "Promotion-Sub_LOB2_Label": {},
    "rdLTMInternship": {},
    "rdPRInternship": {},
    "Rectangle1": {},
    "Rectangle2": {},
    "Rectangle3": {},
    "Rectangle3_1": {},
    "REGULARIZATION DATE_Column1": {},
    "Reminder": {},
    "Remove Button Container": {},
    "Remove_BTN": {},
    "Remove_Button": {},
    "REMOVE_BUTTON": {},
    "ROLE_Column1_1": {},
    "ROLE_DataCardOCFP": {},
    "Roster Update Selection": {},
    "Save Button Container": {},
    "Save_Button": {},
    "SAVE_BUTTON": {},
    "SAVE_BUTTON_LT": {},
    "SCHEDULE_OTDataCard": {},
    "SCHEDULE_OTDataCard1": {},
    "Separator2": {},
    "Separator2_1": {},
    "Separator2_1_Verify_1": {},
    "Separator3": {},
    "Separator3_1": {},
    "Separator4": {},
    "Separator4_2": {},
    "Separator4_2_Verify_1": {},
    "SITE DataCard PRMp1_1": {},
    "SITE_Column1_1": {},
    "Site_DataCard": {},
    "SITE_LTMDataCard": {},
    "SITE_LTMDataCard2": {},
    "SITE_OTDataCard": {},
    "SITE_OTDataCard1": {},
    "SITE_PRMDataCard_4": {},
    "START DATE_OTDataCard": {},
    "START DATE_OTDataCard1": {},
    "StarVisible1": {},
    "StarVisible2": {},
    "StarVisible3": {},
    "STATUS_Column1": {},
    "STATUS_DataCardOCFP": {},
    "STATUS_OTDataCard": {},
    "STATUS_OTDataCard1": {},
    "Sub-LOB": {},
    "SUB-LOB": {},
    "SUB-LOB_Column1_1": {},
    "Sub-LOB_DataCard": {},
    "SUB-LOB_DataCardOCFP": {},
    "SUB-LOB_OTDataCard": {},
    "SUB-LOB2_OTDataCard": {},
    "SUB-UNIT_Column1": {},
    "SUB-UNIT_DataCard PRMp1_1": {},
    "SUB-UNIT_DataCardOCFP": {},
    "SUB-UNIT_LTMDataCard": {},
    "SUB-UNIT_LTMDataCard2": {},
    "SUB-UNIT_OTDataCard": {},
    "SUB-UNIT_OTDataCard1": {},
    "SUB-UNIT_PRMDataCard2_2": {},
    "SUPERVISOR EMP ID": {},
    "SUPERVISOR EMP ID_Column1": {},
    "supervisor_card": {},
    "supervisor_card_1": {},
    "SUPERVISOR_Column1_1": {},
    "SUPERVISOR_DataCard PRMp1_1": {},
    "SUPERVISOR_EMAIL": {},
    "SUPERVISOR_EMAIL_LT": {},
    "supervisor_emp_id": {},
    "SUPERVISOR_EMP_ID": {},
    "SUPERVISOR_EMP_ID_PRMDataCard": {},
    "SUPERVISOR_LT": {},
    "SUPERVISOR_LTMDataCard": {},
    "SUPERVISOR_OTDataCard": {},
    "SUPERVISOR_OTDataCard1": {},
    "supervisor_value": {},
    "SupervisorEmail": {},
    "supervisorEmpID_1": {},
    "supervisorEmpID_value": {},
    "SUPERVISORS_EMAIL_LT": {},
    "tblOCSP": {},
    "TEAM_PRMDataCard2_2": {},
    "TEAMLEADEREMP.ID_DataCard1": {},
    "TEAMLEADEREMP.ID_DataCard2": {},
    "TEAMLEADEREMP.ID_DataCard3": {},
    "Termination Status Verify": {},
    "Termination_FirstPage": {},
    "Termination_VerificationPage": {},
    "terminationStatus_card": {},
    "terminationStatus_card_1": {},
    "terminationStatus_cb": {},
    "terminationStatus_label": {},
    "terminationStatus_label_1": {},
    "terminationType_card": {},
    "terminationType_card_1": {},
    "terminationType_cb": {},
    "terminationType_label": {},
    "terminationType_label_1": {},
    "Time_Zone": {},
    "TIME_ZONE": {},
    "trainer1": {},
    "Trainer1": {},
    "TRAINER1": {},
    "trainer2": {},
    "Trainer2": {},
    "TRAINER2": {},
    "trainer3": {},
    "Trainer3": {},
    "TRAINER3": {},
    "Treehouse Guide Group": {},
    "txtLTMultipleBillability2": {},
    "txtLTMultipleBusUnit2": {},
    "txtLTMultipleEmpId": {},
    "txtLTMultipleEmpId2": {},
    "txtLTMultipleName": {},
    "txtLTMultipleName_1": {},
    "txtLTMultipleName_2": {},
    "txtLTMultipleName_3": {},
    "txtLTMultipleOmnia": {},
    "txtLTMultipleOmnia_1": {},
    "txtLTMultipleOmnia_2": {},
    "txtLTMultiplePosition2": {},
    "txtLTMultipleSite": {},
    "txtLTMultipleSite2": {},
    "txtLTMultipleSubUnit2": {},
    "txtLTMutipleClient2": {},
    "txtLTSearchMultipleLOB": {},
    "txtLTSearchMultipleOmnia": {},
    "txtOCEPClassName": {},
    "txtOCEPEmpId": {},
    "txtOCEPFName": {},
    "txtOCEPInternalEmail": {},
    "txtOCEPLName": {},
    "txtOCEPMName": {},
    "txtOCEPSupervisorEmpID": {},
    "txtOCFPClassName": {},
    "txtOCFPEmpId": {},
    "txtOCFPFName": {},
    "txtOCFPLName": {},
    "txtOCFPMName": {},
    "txtOCFPSupervisorEmpId": {},
    "txtOCInternalEmail": {},
    "txtOTBillability1": {},
    "txtOTBusUnit1": {},
    "txtOTClient1": {},
    "txtOTEmpId": {},
    "txtOTEmpId1": {},
    "txtOTEndDate1": {},
    "txtOTLOB": {},
    "txtOTLOB1": {},
    "txtOTMName": {},
    "txtOTMOmnia": {},
    "txtOTNesting1": {},
    "txtOTOmnia": {},
    "txtOTPosition1": {},
    "txtOTProduction1": {},
    "txtOTSchedule": {},
    "txtOTSchedule1": {},
    "txtOTSite": {},
    "txtOTSite1": {},
    "txtOTStartdate1": {},
    "txtOTStatus1": {},
    "txtOTSubUnit1": {},
    "txtOTSupervisor1": {},
    "txtPREDp1_1": {},
    "txtPREDp2_1": {},
    "txtPRMultipleBILLpm2_1": {},
    "txtPRMultipleBUpm2_1": {},
    "txtPRMultipleCLpm2_1": {},
    "txtPRMultipleEmpName_1": {},
    "txtPRMultipleEmpNamepm2_1": {},
    "txtPRMultipleNamepm1_1": {},
    "txtPRMultipleOmniapm1": {},
    "txtPRMultipleOmniapm2_1": {},
    "txtPRMultiplePOSpm2_1": {},
    "txtPRMultipleSite_1": {},
    "txtPRMultipleSitepm2_1": {},
    "txtPRMultipleSUpm2_1": {},
    "txtPRMultipleSUPpm2_1": {},
    "txtPRSearchMultipleLOB_1": {},
    "txtPRSearchMultipleOmnia_1": {},
    "txtPRSEp1_1": {},
    "txtPRUEp2_1": {}
  },
  "PCFDynamicSchemaForIRRetrievalEntry": {},
  "PCFTemplateEntry": {},
  "PublishOrderIndices": {
    "address_card": 662,
    "address_card_1": 719,
    "address_input": 664,
    "address_input_1": 721,
    "address_label": 663,
    "address_label_1": 720,
    "ALVARIA ID_Column1": 126,
    "Alvaria_ID": 87,
    "App": 0,
    "BILLABILITY_Column1_1": 120,
    "BILLABILITY_DataCard PRMp1_1": 535,
    "BILLABILITY_DataCardOCFP": 68,
    "BILLABILITY_LTMDataCard": 247,
    "BILLABILITY_LTMDataCard2": 305,
    "BILLABILITY_OTDataCard": 367,
    "BILLABILITY_OTDataCard1": 449,
    "BILLABILITY_PRMDataCard2_2": 593,
    "btnFirstPageNext": 7,
    "btnLTMultipleBack": 266,
    "btnLTMultipleBack_1": 322,
    "btnLTMultipleBack_2": 490,
    "btnLTMultipleBack_3": 670,
    "btnLTMultipleBack_4": 727,
    "btnLTMultipleReview": 267,
    "btnLTMultipleReview_1": 323,
    "btnLTMultipleReview_2": 491,
    "btnLTRemove": 321,
    "btnLTRemove_1": 726,
    "btnOCEPBack": 201,
    "btnOCEPUpdate": 203,
    "btnOCFPBack": 96,
    "btnOCFPReview": 97,
    "btnOCFPSave": 95,
    "btnOCSPBack": 127,
    "btnOCSPEdit": 99,
    "btnOCSPRemove": 101,
    "btnOCSPSubmit": 129,
    "btnOTBack": 410,
    "btnOTRemove": 489,
    "btnOTReview": 411,
    "btnOTSave": 409,
    "btnPRMultipleBackp1_1": 554,
    "btnPRMultipleBackp2_1": 610,
    "btnPRMultipleReviewp1_1": 555,
    "btnPRMultipleSubmitp2_1": 611,
    "btnPRRemovep2_3": 609,
    "BUSINESS UNIT_Column1_1": 112,
    "BUSINESS UNIT_DataCard PRMp1_1": 514,
    "BUSINESS UNIT_DataCardOCFP": 40,
    "BUSINESS UNIT_LTMDataCard": 226,
    "BUSINESS UNIT_LTMDataCard2": 284,
    "BUSINESS UNIT_OTDataCard": 349,
    "BUSINESS UNIT_OTDataCard1": 431,
    "BUSINESS UNIT_PRMDataCard_4": 572,
    "Button1": 94,
    "Button2": 669,
    "Button5": 553,
    "Button6": 265,
    "campaign_card": 641,
    "campaign_card_1": 698,
    "CAMPAIGN_Column1_1": 116,
    "campaign_label": 642,
    "campaign_label_1": 699,
    "campaign_value": 643,
    "campaign_value_1": 700,
    "cbLTMultipleBillability": 248,
    "cbLTMultipleBusUnit": 227,
    "cbLTMultipleClient": 239,
    "cbLTMultipleLOB": 242,
    "cbLTMultiplePosition": 233,
    "cbLTMultipleSubLOB": 245,
    "cbLTMultipleSubUnit": 230,
    "cbLTMultipleSupervisor": 251,
    "cbLTMultipleSupervisorEmail_1": 254,
    "cbLTMultipleSupervisorEmpID_1": 257,
    "cbLTSearchMultipleLOB": 207,
    "cbLTSearchMultipleOmnia": 209,
    "cbOCEPAlvariaID": 177,
    "cbOCEPBillability": 180,
    "cbOCEPBusUnit": 143,
    "cbOCEPCampaign": 144,
    "cbOCEPClient": 199,
    "cbOCEPCountry": 141,
    "cbOCEPEmpStatus": 189,
    "cbOCEPLOB": 155,
    "cbOCEPPosition": 167,
    "cbOCEPRole": 165,
    "cbOCEPSite": 153,
    "cbOCEPStatus": 179,
    "cbOCEPSubLOB": 168,
    "cbOCEPSubUnit": 156,
    "cbOCEPSupervisor": 190,
    "cbOCFPAlvariaID": 89,
    "cbOCFPBillability": 70,
    "cbOCFPBusUnit": 42,
    "cbOCFPClient": 57,
    "cbOCFPCountry": 83,
    "cbOCFPDivision": 61,
    "cbOCFPEmpStatus": 54,
    "cbOCFPLOB": 64,
    "cbOCFPPosition": 48,
    "cbOCFPRole": 86,
    "cbOCFPSite": 80,
    "cbOCFPStatus": 51,
    "cbOCFPSubLOB": 67,
    "cbOCFPSubUnit": 45,
    "cbOCFPSupervisor": 73,
    "cbOTBillability": 368,
    "cbOTBusUnit": 350,
    "cbOTClient": 362,
    "cbOTLOB": 403,
    "cbOTOmnia": 327,
    "cbOTPosition": 397,
    "cbOTSearchLOB": 329,
    "cbOTStatus": 353,
    "cbOTSub-LOB": 344,
    "cbOTSubUnit": 356,
    "cbOTSupervisor": 383,
    "cbOTSupervisorEmpID": 389,
    "cbPRMultipleBillability_1": 536,
    "cbPRMultipleBusUnit_1": 515,
    "cbPRMultipleClient_1": 527,
    "cbPRMultipleLOB_2": 530,
    "cbPRMultiplePosition_1": 521,
    "cbPRMultipleSub-LOB": 533,
    "cbPRMultipleSubUnit_1": 518,
    "cbPRMultipleSupervisor_1": 539,
    "cbPRMultipleSupervisorEmail_1": 547,
    "cbPRMultipleSupervisorEmpID_1": 542,
    "cbPRSearchMultipleLOB": 496,
    "cbPRSearchMultipleOmnia": 497,
    "CLASS NAME_Column1": 117,
    "class_name": 406,
    "Class_Name": 485,
    "CLASS_NAME": 407,
    "ClassName": 405,
    "CLIENT_Column1_1": 115,
    "CLIENT_DataCard PRMp1_1": 526,
    "CLIENT_LTMDataCard": 238,
    "CLIENT_LTMDataCard2": 296,
    "CLIENT_OTDataCard": 361,
    "CLIENT_OTDataCard1": 443,
    "CLIENT_PRMDataCard2_2": 584,
    "comment_card": 665,
    "comment_card_1": 722,
    "comment_input": 667,
    "comment_input_1": 724,
    "comment_label": 666,
    "comment_label_1": 723,
    "COUNTRY_Column1_1": 123,
    "Country_DataCard": 74,
    "Country_DataCard1": 81,
    "CS FreshService": 12,
    "CS FreshService Group": 9,
    "DataCard10": 90,
    "DataCard2": 55,
    "DataCard3": 71,
    "DataCard7": 293,
    "DataCard8": 59,
    "DataCardKey1": 279,
    "DataCardKey1_1": 423,
    "DataCardKey10": 31,
    "DataCardKey11": 37,
    "DataCardKey12": 259,
    "DataCardKey13": 372,
    "DataCardKey14": 378,
    "DataCardKey15": 391,
    "DataCardKey15_1": 44,
    "DataCardKey16": 544,
    "DataCardKey16_1": 47,
    "DataCardKey18": 453,
    "DataCardKey19": 459,
    "DataCardKey2": 243,
    "DataCardKey24": 221,
    "DataCardKey24_1": 341,
    "DataCardKey27": 435,
    "DataCardKey28": 441,
    "DataCardKey29": 447,
    "DataCardKey3": 531,
    "DataCardKey35": 66,
    "DataCardKey36": 288,
    "DataCardKey36_1": 438,
    "DataCardKey37": 228,
    "DataCardKey37_1": 285,
    "DataCardKey37_2": 351,
    "DataCardKey37_3": 432,
    "DataCardKey38": 231,
    "DataCardKey38_1": 357,
    "DataCardKey39": 240,
    "DataCardKey39_1": 363,
    "DataCardKey4": 300,
    "DataCardKey40": 249,
    "DataCardKey40_1": 369,
    "DataCardKey41": 234,
    "DataCardKey41_1": 398,
    "DataCardKey42": 252,
    "DataCardKey42_1": 384,
    "DataCardKey43_1": 375,
    "DataCardKey44": 291,
    "DataCardKey44_1": 477,
    "DataCardKey45": 297,
    "DataCardKey45_1": 444,
    "DataCardKey46": 63,
    "DataCardKey47": 224,
    "DataCardKey47_1": 282,
    "DataCardKey47_2": 347,
    "DataCardKey47_3": 429,
    "DataCardKey48": 69,
    "DataCardKey5": 404,
    "DataCardKey50": 306,
    "DataCardKey50_1": 450,
    "DataCardKey51_1": 456,
    "DataCardKey52_1": 465,
    "DataCardKey55": 85,
    "DataCardKey56": 22,
    "DataCardKey6": 25,
    "DataCardKey7": 483,
    "DataCardKey8": 588,
    "DataCardKey9": 28,
    "DataCardKeyBILLpm1_1": 537,
    "DataCardKeyBILLPRpm2_1": 594,
    "DataCardKeyBUpm1_1": 516,
    "DataCardKeyBUPRpm2_1": 573,
    "DataCardKeyCLpm1_1": 528,
    "DataCardKeyCLPRpm2_1": 585,
    "DataCardKeyENpm1_1": 509,
    "DataCardKeyENPRpm2_1": 567,
    "DataCardKeyPOSpm1_1": 522,
    "DataCardKeyPOSPRpm2_1": 579,
    "DataCardKeySITEpm1_1": 512,
    "DataCardKeySITEPRpm2_1": 570,
    "DataCardKeySUpm1_1": 519,
    "DataCardKeySUPpm1_1": 540,
    "DataCardKeySUPPRpm2_1": 597,
    "DataCardKeySUPRpm2_1": 576,
    "DataCardValue2": 301,
    "DataCardValue4": 589,
    "dateEnd": 365,
    "dateNesting": 371,
    "dateOCEPHireDate": 188,
    "dateOCFPHireDate": 38,
    "dateProduction": 377,
    "dateStart": 359,
    "dpLTEffectivityDate": 262,
    "dpPREffectivityDate": 550,
    "drpOTtimezone": 380,
    "drpRosterSelection": 5,
    "EFFECTIVITY_DATE": 549,
    "EFFECTIVITY_DATE_LT": 261,
    "EffectivityDate": 605,
    "effectivityDate_card": 656,
    "effectivityDate_card_1": 713,
    "effectivityDate_input": 658,
    "effectivityDate_input_1": 715,
    "effectivityDate_label": 657,
    "effectivityDate_label_1": 714,
    "EFFECTIVITYDATE_LT": 317,
    "email_card": 638,
    "email_card_1": 695,
    "email_label": 639,
    "email_label_1": 696,
    "email_value": 640,
    "email_value_1": 697,
    "EMPLOYEE ID_Column1_1": 103,
    "EMPLOYEE ID_DataCard1": 278,
    "EMPLOYEE ID_DataCardOCFP": 21,
    "EMPLOYEE ID_LTMDataCard": 220,
    "EMPLOYEE ID_OTDataCard": 340,
    "EMPLOYEE ID_OTDataCard1": 422,
    "EMPLOYEE NAME_PRMDataCard_3": 566,
    "EmployeeGallery": 619,
    "EmployeeGallery_1": 675,
    "employeeID_1": 680,
    "EmployeeInfo_form": 625,
    "EmployeeInfo_form_1": 682,
    "employeeInfo_label": 618,
    "employeeInfo_label_1": 674,
    "employeeList_label": 617,
    "employeeList_label_1": 673,
    "employeeName": 621,
    "employeeName_1": 677,
    "EMPLOYEESTATUS_DataCard12": 52,
    "EMPLOYMENT STATUS_Column1": 111,
    "END DATE_OTDataCard": 364,
    "END DATE_OTDataCard1": 446,
    "ErrorMessage1": 260,
    "ErrorMessage2": 392,
    "ErrorMessage3": 545,
    "FIRST NAME_Column1_1": 104,
    "FIRST NAME_DataCardOCFP": 24,
    "fname_card": 626,
    "fname_card_1": 683,
    "fname_label": 627,
    "fname_label_1": 684,
    "fname_value": 628,
    "fname_value_1": 685,
    "formLTM": 219,
    "formLTM2": 277,
    "formOCFirstPage1": 20,
    "formOCFirstPage2": 39,
    "formOCFirstPage3": 58,
    "formOCFirstPage4": 77,
    "formOT": 339,
    "formOT1": 421,
    "formPREDsp2": 507,
    "formPREDsp2_1": 565,
    "FULL NAME_DataCard PRMp1_1": 508,
    "galleryLTM": 213,
    "galleryLTM_1": 271,
    "galleryLTM_2": 415,
    "galleryOT": 333,
    "galleryPRMp1st_1": 501,
    "galleryPRMp2nd_1": 559,
    "galleryTemplate2": 214,
    "galleryTemplate2_1": 272,
    "galleryTemplate2_2": 334,
    "galleryTemplate2_3": 416,
    "galleryTemplate2_4": 502,
    "galleryTemplate2_5": 560,
    "galleryTemplate3": 620,
    "galleryTemplate3_1": 676,
    "galleryTemplate6": 132,
    "galOCEP": 131,
    "grpLTSearchMultipleLOB": 206,
    "grpLTSearchMultipleOmnia": 208,
    "grpNewOCForm": 17,
    "grpOCECountry": 134,
    "grpOCEPBillability": 176,
    "grpOCEPBusUnit": 138,
    "grpOCEPButtons": 202,
    "grpOCEPCampaign": 140,
    "grpOCEPClient": 195,
    "grpOCEPEmpId": 136,
    "grpOCEPEmpStatus": 185,
    "grpOCEPFName": 146,
    "grpOCEPHireDate": 183,
    "grpOCEPInternalEmail": 193,
    "grpOCEPLName": 172,
    "grpOCEPLOB": 152,
    "grpOCEPMName": 160,
    "grpOCEPPosition": 164,
    "grpOCEPRole": 158,
    "grpOCEPRole_1": 170,
    "grpOCEPSite": 148,
    "grpOCEPStatus": 174,
    "grpOCEPSubLOB": 162,
    "grpOCEPSubUnit": 150,
    "grpOCEPSupervisor": 187,
    "grpOCFPButtons": 18,
    "grpOCSPActions": 100,
    "grpOCSPButtons": 128,
    "grpOTLOB": 325,
    "grpOTOmnia": 326,
    "grpPRSearchMultipleLOB_1": 493,
    "grpPRSearchMultipleOmnia_1": 494,
    "HIRE DATE_Column1_1": 108,
    "HIRE DATE_DataCardOCFP": 36,
    "HomePage": 2,
    "Host": 0,
    "Image2": 13,
    "INTERNAL EMAIL": 33,
    "INTERNAL EMAIL_Column1": 107,
    "INTERNSHIP_DataCard": 523,
    "INTERNSHIP_LTMDataCard": 235,
    "INTERNSHIP_PRMDataCard_2": 581,
    "Label1": 709,
    "Label10": 401,
    "Label11": 582,
    "Label12": 583,
    "Label13": 236,
    "Label14": 487,
    "Label15": 295,
    "Label16": 294,
    "Label17": 468,
    "Label18": 381,
    "Label19": 2,
    "Label19_1": 6,
    "Label2": 354,
    "Label20": 462,
    "Label21": 463,
    "Label22": 60,
    "Label23": 3,
    "Label24": 79,
    "Label25": 41,
    "Label26": 474,
    "Label27": 50,
    "Label28": 480,
    "Label29": 53,
    "Label3": 360,
    "Label30": 469,
    "Label31": 481,
    "Label32": 486,
    "Label33": 475,
    "Label34": 318,
    "Label35": 319,
    "Label36": 309,
    "Label37": 34,
    "Label38": 310,
    "Label39": 551,
    "Label4": 366,
    "Label40": 606,
    "Label41": 607,
    "Label42": 14,
    "Label42_1": 15,
    "Label43": 192,
    "Label44": 548,
    "Label45": 255,
    "Label46": 600,
    "Label47": 601,
    "Label48": 312,
    "Label49": 313,
    "Label5": 135,
    "Label5_1": 145,
    "Label5_10": 194,
    "Label5_11": 139,
    "Label5_12": 151,
    "Label5_13": 161,
    "Label5_14": 186,
    "Label5_15": 133,
    "Label5_16": 147,
    "Label5_17": 157,
    "Label5_18": 175,
    "Label5_19": 169,
    "Label5_2": 159,
    "Label5_20": 196,
    "Label5_21": 181,
    "Label5_3": 171,
    "Label5_4": 182,
    "Label5_5": 137,
    "Label5_6": 149,
    "Label5_7": 163,
    "Label5_8": 184,
    "Label5_9": 173,
    "Label50": 56,
    "Label51": 72,
    "Label52": 75,
    "Label53": 88,
    "Label54": 93,
    "Label54_1": 197,
    "Label55": 246,
    "Label56": 303,
    "Label57": 304,
    "Label58": 534,
    "Label59": 82,
    "Label6": 263,
    "Label60": 592,
    "Label61": 345,
    "Label62": 426,
    "Label63": 427,
    "Label64": 91,
    "Label65": 315,
    "Label66": 316,
    "Label67": 471,
    "Label68": 472,
    "Label69": 603,
    "Label7": 524,
    "Label70": 604,
    "Label71": 645,
    "Label73": 648,
    "Label75": 702,
    "Label76": 703,
    "Label77": 705,
    "Label78": 706,
    "Label8": 387,
    "Label9": 395,
    "LAST NAME_Column1_1": 106,
    "LAST NAME_DataCardOCFP": 30,
    "lastDate_card": 659,
    "lastDate_card_1": 716,
    "lastDate_input": 661,
    "lastDate_input_1": 718,
    "lastDate_label": 660,
    "lastDate_label_1": 717,
    "Lateral Transfer Form_1": 204,
    "Lateral Transfer Form_2": 211,
    "Lateral Transfer Form_3": 212,
    "Lateral Transfer Form_4": 268,
    "Lateral Transfer Form_5": 269,
    "Lateral Transfer Form_6": 270,
    "LateralTransfer_FirstPage": 0,
    "LateralTransfer_SecondPage": 0,
    "LineOfBusiness_Label_1": 615,
    "lname_card": 629,
    "lname_card_1": 686,
    "lname_label": 630,
    "lname_label_1": 688,
    "lname_value": 631,
    "lname_value_1": 687,
    "lob_card": 635,
    "lob_card_1": 692,
    "LOB_Column1_1": 118,
    "LOB_DataCard1": 241,
    "LOB_DataCard2": 529,
    "LOB_DataCard3": 299,
    "LOB_DataCard4": 402,
    "LOB_DataCard7": 587,
    "LOB_DataCardOCFP": 62,
    "lob_input": 614,
    "lob_label": 636,
    "lob_Label": 613,
    "lob_label_1": 694,
    "LOB_OTDataCard1": 482,
    "lob_value": 637,
    "lob_value_1": 693,
    "MIDDLE NAME_Column1_1": 105,
    "MIDDLE NAME_DataCardOCFP": 27,
    "MultipleTerminationForm_Label": 612,
    "MultipleTerminationForm_Label_1": 672,
    "NESTING START DATE_DataCard1": 370,
    "NESTING START DATE_DataCard3": 452,
    "NewHireOnboarding_EditPage": 0,
    "NewHireOnboarding_FirstPage": 0,
    "NewHireOnboarding_SecondPage": 0,
    "NextArrow2": 216,
    "NextArrow2_1": 336,
    "NextArrow2_1_Verify_1": 504,
    "NextArrow3": 274,
    "NextArrow3_1": 418,
    "NextArrow4": 622,
    "NextArrow4_2": 678,
    "NextArrow4_2_Verify_1": 562,
    "oc1": 16,
    "oc2": 98,
    "oc3": 130,
    "omnia_input": 616,
    "omniaID": 623,
    "omniaID_1": 679,
    "OT1": 324,
    "OT2": 332,
    "OT3": 331,
    "OT4": 414,
    "OT5": 413,
    "OT6": 412,
    "Others_FirstPage": 0,
    "Others_SecondPage": 0,
    "position_card": 632,
    "position_card_1": 689,
    "POSITION_Column1_1": 114,
    "POSITION_DataCard PRMp1_1": 520,
    "POSITION_DataCardOCFP": 46,
    "position_label": 633,
    "position_label_1": 690,
    "POSITION_LTMDataCard": 232,
    "POSITION_LTMDataCard2": 290,
    "POSITION_OTDataCard": 396,
    "POSITION_OTDataCard1": 476,
    "POSITION_PRMDataCard2_2": 578,
    "position_value": 634,
    "position_value_1": 691,
    "proceed_btn": 671,
    "proceed_btn_1": 728,
    "PRODUCTION DATE_DataCard1": 376,
    "PRODUCTION DATE_DataCard3": 458,
    "Promotion Form p2_1": 556,
    "Promotion Form_1": 492,
    "Promotion_FirstPage": 314,
    "Promotion_SecondPage": 362,
    "Promotion-Sub_LOB2": 590,
    "Promotion-Sub_LOB2_Label": 591,
    "rdLTMInternship": 237,
    "rdPRInternship": 525,
    "Rectangle1": 19,
    "Rectangle2": 0,
    "Rectangle3": 8,
    "Rectangle3_1": 10,
    "REGULARIZATION DATE_Column1": 109,
    "Reminder": 1,
    "Remove Button Container": 725,
    "Remove_BTN": 320,
    "Remove_Button": 608,
    "REMOVE_BUTTON": 488,
    "ROLE_Column1_1": 125,
    "ROLE_DataCardOCFP": 84,
    "Roster Update Selection": 4,
    "Save Button Container": 668,
    "Save_Button": 408,
    "SAVE_BUTTON": 552,
    "SAVE_BUTTON_LT": 264,
    "SCHEDULE_OTDataCard": 373,
    "SCHEDULE_OTDataCard1": 455,
    "Separator2": 218,
    "Separator2_1": 338,
    "Separator2_1_Verify_1": 506,
    "Separator3": 276,
    "Separator3_1": 420,
    "Separator4": 624,
    "Separator4_2": 681,
    "Separator4_2_Verify_1": 564,
    "SITE DataCard PRMp1_1": 511,
    "SITE_Column1_1": 124,
    "Site_DataCard": 78,
    "SITE_LTMDataCard": 223,
    "SITE_LTMDataCard2": 281,
    "SITE_OTDataCard": 346,
    "SITE_OTDataCard1": 428,
    "SITE_PRMDataCard_4": 569,
    "START DATE_OTDataCard": 358,
    "START DATE_OTDataCard1": 440,
    "StarVisible1": 258,
    "StarVisible2": 390,
    "StarVisible3": 543,
    "STATUS_Column1": 110,
    "STATUS_DataCardOCFP": 49,
    "STATUS_OTDataCard": 352,
    "STATUS_OTDataCard1": 434,
    "Sub-LOB": 532,
    "SUB-LOB": 302,
    "SUB-LOB_Column1_1": 119,
    "Sub-LOB_DataCard": 244,
    "SUB-LOB_DataCardOCFP": 65,
    "SUB-LOB_OTDataCard": 343,
    "SUB-LOB2_OTDataCard": 425,
    "SUB-UNIT_Column1": 113,
    "SUB-UNIT_DataCard PRMp1_1": 517,
    "SUB-UNIT_DataCardOCFP": 43,
    "SUB-UNIT_LTMDataCard": 229,
    "SUB-UNIT_LTMDataCard2": 287,
    "SUB-UNIT_OTDataCard": 355,
    "SUB-UNIT_OTDataCard1": 437,
    "SUB-UNIT_PRMDataCard2_2": 575,
    "SUPERVISOR EMP ID": 314,
    "SUPERVISOR EMP ID_Column1": 122,
    "supervisor_card": 644,
    "supervisor_card_1": 701,
    "SUPERVISOR_Column1_1": 121,
    "SUPERVISOR_DataCard PRMp1_1": 538,
    "SUPERVISOR_EMAIL": 546,
    "SUPERVISOR_EMAIL_LT": 253,
    "supervisor_emp_id": 647,
    "SUPERVISOR_EMP_ID": 470,
    "SUPERVISOR_EMP_ID_PRMDataCard": 602,
    "SUPERVISOR_LT": 308,
    "SUPERVISOR_LTMDataCard": 250,
    "SUPERVISOR_OTDataCard": 382,
    "SUPERVISOR_OTDataCard1": 464,
    "supervisor_value": 646,
    "SupervisorEmail": 599,
    "supervisorEmpID_1": 704,
    "supervisorEmpID_value": 649,
    "SUPERVISORS_EMAIL_LT": 311,
    "tblOCSP": 102,
    "TEAM_PRMDataCard2_2": 596,
    "TEAMLEADEREMP.ID_DataCard1": 256,
    "TEAMLEADEREMP.ID_DataCard2": 388,
    "TEAMLEADEREMP.ID_DataCard3": 541,
    "Termination Status Verify": 712,
    "Termination_FirstPage": 208,
    "Termination_VerificationPage": 264,
    "terminationStatus_card": 653,
    "terminationStatus_card_1": 710,
    "terminationStatus_cb": 655,
    "terminationStatus_label": 654,
    "terminationStatus_label_1": 711,
    "terminationType_card": 650,
    "terminationType_card_1": 707,
    "terminationType_cb": 652,
    "terminationType_label": 651,
    "terminationType_label_1": 708,
    "Time_Zone": 379,
    "TIME_ZONE": 461,
    "trainer1": 386,
    "Trainer1": 467,
    "TRAINER1": 385,
    "trainer2": 394,
    "Trainer2": 473,
    "TRAINER2": 393,
    "trainer3": 400,
    "Trainer3": 479,
    "TRAINER3": 399,
    "Treehouse Guide Group": 11,
    "txtLTMultipleBillability2": 307,
    "txtLTMultipleBusUnit2": 286,
    "txtLTMultipleEmpId": 222,
    "txtLTMultipleEmpId2": 280,
    "txtLTMultipleName": 215,
    "txtLTMultipleName_1": 273,
    "txtLTMultipleName_2": 417,
    "txtLTMultipleName_3": 561,
    "txtLTMultipleOmnia": 217,
    "txtLTMultipleOmnia_1": 275,
    "txtLTMultipleOmnia_2": 419,
    "txtLTMultiplePosition2": 292,
    "txtLTMultipleSite": 225,
    "txtLTMultipleSite2": 283,
    "txtLTMultipleSubUnit2": 289,
    "txtLTMutipleClient2": 298,
    "txtLTSearchMultipleLOB": 205,
    "txtLTSearchMultipleOmnia": 210,
    "txtOCEPClassName": 191,
    "txtOCEPEmpId": 142,
    "txtOCEPFName": 154,
    "txtOCEPInternalEmail": 198,
    "txtOCEPLName": 178,
    "txtOCEPMName": 166,
    "txtOCEPSupervisorEmpID": 200,
    "txtOCFPClassName": 92,
    "txtOCFPEmpId": 23,
    "txtOCFPFName": 26,
    "txtOCFPLName": 32,
    "txtOCFPMName": 29,
    "txtOCFPSupervisorEmpId": 76,
    "txtOCInternalEmail": 35,
    "txtOTBillability1": 451,
    "txtOTBusUnit1": 433,
    "txtOTClient1": 445,
    "txtOTEmpId": 342,
    "txtOTEmpId1": 424,
    "txtOTEndDate1": 448,
    "txtOTLOB": 328,
    "txtOTLOB1": 484,
    "txtOTMName": 335,
    "txtOTMOmnia": 337,
    "txtOTNesting1": 454,
    "txtOTOmnia": 330,
    "txtOTPosition1": 478,
    "txtOTProduction1": 460,
    "txtOTSchedule": 374,
    "txtOTSchedule1": 457,
    "txtOTSite": 348,
    "txtOTSite1": 430,
    "txtOTStartdate1": 442,
    "txtOTStatus1": 436,
    "txtOTSubUnit1": 439,
    "txtOTSupervisor1": 466,
    "txtPREDp1_1": 500,
    "txtPREDp2_1": 558,
    "txtPRMultipleBILLpm2_1": 595,
    "txtPRMultipleBUpm2_1": 574,
    "txtPRMultipleCLpm2_1": 586,
    "txtPRMultipleEmpName_1": 510,
    "txtPRMultipleEmpNamepm2_1": 568,
    "txtPRMultipleNamepm1_1": 503,
    "txtPRMultipleOmniapm1": 505,
    "txtPRMultipleOmniapm2_1": 563,
    "txtPRMultiplePOSpm2_1": 580,
    "txtPRMultipleSite_1": 513,
    "txtPRMultipleSitepm2_1": 571,
    "txtPRMultipleSUpm2_1": 577,
    "txtPRMultipleSUPpm2_1": 598,
    "txtPRSearchMultipleLOB_1": 495,
    "txtPRSearchMultipleOmnia_1": 498,
    "txtPRSEp1_1": 499,
    "txtPRUEp2_1": 557
  },
  "ResourcesJsonIndices": {
    "Image-bit.ly_CSFreshService": 6,
    "Image-bit.ly_DynamicRosterUpdateApplication-Treehouse": 7,
    "Image-homeScreen": 4,
    "Image-homeScreen2": 5,
    "Image-MicrosoftTeams-image": 2,
    "Image-MicrosoftTeams-image (2)": 1,
    "Image-SampleImage": 0,
    "Image-Untitled design 29": 3
  },
  "RuleScreenIdWithoutScreen": {},
  "TemplateVersions": {},
  "VolatileProperties": {
    "AnalysisLoadTime": 2.6705465,
    "ControlCount": {
      "button": 35,
      "combobox": 66,
      "dataTable": 1,
      "dataTableColumn": 24,
      "datepicker": 12,
      "dropdown": 4,
      "form": 12,
      "gallery": 9,
      "galleryTemplate": 9,
      "group": 35,
      "htmlViewer": 12,
      "icon": 8,
      "image": 2,
      "label": 302,
      "radio": 2,
      "rectangle": 12,
      "screen": 12,
      "text": 25,
      "typedDataCard": 159
    },
    "DeserializationLoadTime": 3.8460048
  },
  "WasLocalDatabaseReferencesEmpty": true
}